Workbook

Sheet SweepValue1
A1: CASE VARIABLES | B1: source capacity
A2: SWEEP VALUE | B2: 1
A4: END TIME | B4: 2
A5: NUM STEPS | B5: 21
A6: PROJECT TIME | B6: 20
A7: DISCOUNT RATE | B7: 0.08
A8: Inflation | B8: 0
A9: Tax | B9: 0.25
A11: YEAR 1
B12: Time | C12: 0 | D12: 0.1 | E12: 0.2 | F12: 0.3 | G12: 0.4 | H12: 0.5 | I12: 0.6 | J12: 0.7 | K12: 0.8 | L12: 0.9 | M12: 1 | N12: 1.1 | O12: 1.2 | P12: 1.3 | Q12: 1.4 | R12: 1.5 | S12: 1.6 | T12: 1.7 | U12: 1.8 | V12: 1.9 | W12: 2
B13: Signal | C13: -2.5120128e-10 | D13: 0.06279052 | E13: 0.12533323 | F13: 0.18738131 | G13: 0.24868989 | H13: 0.30901699 | I13: 0.36812455 | J13: 0.42577929 | K13: 0.48175367 | L13: 0.53582679 | M13: 0.58778525 | N13: 0.63742399 | O13: 0.68454711 | P13: 0.72896863 | Q13: 0.77051324 | R13: 0.80901699 | S13: 0.84432793 | T13: 0.87630668 | U13: 0.90482705 | V13: 0.92977649 | W13: 0.95105652
A15: SOURCE | B15: a | C15: =$B$2 -> 1 | D15: =$B$2 -> 1 | E15: =$B$2 -> 1 | F15: =$B$2 -> 1 | G15: =$B$2 -> 1 | H15: =$B$2 -> 1 | I15: =$B$2 -> 1 | J15: =$B$2 -> 1 | ... W15: =$B$2 -> 1
B16: CAPEX Price | C16: 0 | D16: 0 | E16: 0 | F16: 0 | G16: 0 | H16: 0 | I16: 0 | J16: 0 | K16: 0 | L16: 0 | M16: 0 | N16: 0 | O16: 0 | P16: 0 | Q16: 0 | R16: 0 | S16: 0 | T16: 0 | U16: 0 | V16: 0 | W16: 0
B17: CAPEX Cashflow | C17: =C16*(C15/$B$35)^$B$36 -> 0 | D17: =D16*(D15/$B$35)^$B$36 -> 0 | E17: =E16*(E15/$B$35)^$B$36 -> 0 | F17: =F16*(F15/$B$35)^$B$36 -> 0 | G17: =G16*(G15/$B$35)^$B$36 -> 0 | H17: =H16*(H15/$B$35)^$B$36 -> 0 | I17: =I16*(I15/$B$35)^$B$36 -> 0 | J17: =J16*(J15/$B$35)^$B$36 -> 0 | ... W17: =W16*(W15/$B$35)^$B$36 -> 0
B18: FOM Price | C18: =$B$46 -> -100 | D18: 0 | E18: 0 | F18: 0 | G18: 0 | H18: 0 | I18: 0 | J18: 0 | K18: 0 | L18: 0 | M18: 0 | N18: 0 | O18: 0 | P18: 0 | Q18: 0 | R18: 0 | S18: 0 | T18: 0 | U18: 0 | V18: 0 | W18: 0
B19: FOM Cashflow | C19: =C18*(C15/$B$47)^$B$48 -> -10.023052 | D19: =(D15*D16)+(D15*D17)+(D15*D18) -> 0 | E19: =(E15*E16)+(E15*E17)+(E15*E18) -> 0 | F19: =(F15*F16)+(F15*F17)+(F15*F18) -> 0 | G19: =(G15*G16)+(G15*G17)+(G15*G18) -> 0 | H19: =(H15*H16)+(H15*H17)+(H15*H18) -> 0 | I19: =(I15*I16)+(I15*I17)+(I15*I18) -> 0 | J19: =(J15*J16)+(J15*J17)+(J15*J18) -> 0 | K19: =(K15*K16)+(K15*K17)+(K15*K18) -> 0 | ... W19: =(W15*W16)+(W15*W17)+(W15*W18) -> 0
B20: VOM Price | C20: =$B$57 -> -1 | D20: =$B$57 -> -1 | E20: =$B$57 -> -1 | F20: =$B$57 -> -1 | G20: =$B$57 -> -1 | H20: =$B$57 -> -1 | I20: =$B$57 -> -1 | J20: =$B$57 -> -1 | ... W20: =$B$57 -> -1
B21: VOM Cashflow | C21: =(C20*(C15/1)^1)*(1-$B$9) -> -0.75 | D21: =(D20*(D15/1)^1)*(1-$B$9) -> -0.75 | E21: =(E20*(E15/1)^1)*(1-$B$9) -> -0.75 | F21: =(F20*(F15/1)^1)*(1-$B$9) -> -0.75 | G21: =(G20*(G15/1)^1)*(1-$B$9) -> -0.75 | H21: =(H20*(H15/1)^1)*(1-$B$9) -> -0.75 | I21: =(I20*(I15/1)^1)*(1-$B$9) -> -0.75 | J21: =(J20*(J15/1)^1)*(1-$B$9) -> -0.75 | ... W21: =(W20*(W15/1)^1)*(1-$B$9) -> -0.75 | X21: TOTAL
B22: TOTAL Cashflow | C22: =C21+C19+C17 -> -10.773052 | D22: =D21+D19+D17 -> -0.75 | E22: =E21+E19+E17 -> -0.75 | F22: =F21+F19+F17 -> -0.75 | G22: =G21+G19+G17 -> -0.75 | H22: =H21+H19+H17 -> -0.75 | I22: =I21+I19+I17 -> -0.75 | J22: =J21+J19+J17 -> -0.75 | ... W22: =W21+W19+W17 -> -0.75 | X22: =SUM(C22:W22) -> -25.773052
A24: SINK | B24: a | C24: =-$B$2 -> -1 | D24: =-$B$2 -> -1 | E24: =-$B$2 -> -1 | F24: =-$B$2 -> -1 | G24: =-$B$2 -> -1 | H24: =-$B$2 -> -1 | I24: =-$B$2 -> -1 | J24: =-$B$2 -> -1 | ... W24: =-$B$2 -> -1
B25: Sales Price | C25: =$B$68 -> -31.4 | D25: =10 * -3.14 -> -31.4 | E25: =10 * -3.14 -> -31.4 | F25: =10 * -3.14 -> -31.4 | G25: =10 * -3.14 -> -31.4 | H25: =10 * -3.14 -> -31.4 | I25: =10 * -3.14 -> -31.4 | J25: =10 * -3.14 -> -31.4 | K25: =10 * -3.14 -> -31.4 | ... W25: =10 * -3.14 -> -31.4 | X25: TOTAL
B26: Sales Cashflow | C26: =C25*(C24/1)^1 -> 31.4 | D26: =D25*(D24/1)^1 -> 31.4 | E26: =E25*(E24/1)^1 -> 31.4 | F26: =F25*(F24/1)^1 -> 31.4 | G26: =G25*(G24/1)^1 -> 31.4 | H26: =H25*(H24/1)^1 -> 31.4 | I26: =I25*(I24/1)^1 -> 31.4 | J26: =J25*(J24/1)^1 -> 31.4 | ... W26: =W25*(W24/1)^1 -> 31.4 | X26: =SUM(C26:W26) -> 659.4
A28: HOURLY TOTAL | X28: TOTAL
B29: Cashflow | C29: =C26+C22 -> 20.626948 | D29: =D26+D22 -> 30.65 | E29: =E26+E22 -> 30.65 | F29: =F26+F22 -> 30.65 | G29: =G26+G22 -> 30.65 | H29: =H26+H22 -> 30.65 | I29: =I26+I22 -> 30.65 | J29: =J26+J22 -> 30.65 | ... W29: =W26+W22 -> 30.65 | X29: =SUM(C29:W29) -> 633.62695
A32: These numbers are hardcoded from the given heron input file. Changing these values will affect final answer.
A33: CAPEX
A34: reference_price (a) | B34: -10000
A35: reference_driver (D') | B35: 10
A36: scaling_factor (X) | B36: 0.999
A37: driver (D) | B37: =B2 -> 1
A38: type | B38: one-time
A39: period | B39: -
A40: taxable | B40: FALSE
A41: inflation | B41: none
A42: mult_target | B42: FALSE
A43: depreciate | B43: 5
A45: FOM
A46: reference_price (a) | B46: -100
A47: reference_driver (D') | B47: 10
A48: scaling_factor (X) | B48: 0.999
A49: driver (D) | B49: =B2 -> 1
A50: type | B50: repeating
A51: period | B51: year
A52: taxable | B52: FALSE
A53: inflation | B53: none
A54: mult_target | B54: FALSE
A56: VOM
A57: reference_price (a) | B57: -1
A58: reference_driver (D') | B58: 1
A59: scaling_factor (X) | B59: 1
A60: driver (D) | B60: 1
A61: type | B61: repeating
A62: period | B62: -
A63: taxable | B63: TRUE
A64: inflation | B64: none
A65: mult_target | B65: FALSE
A67: Sales
A68: reference_price (a) | B68: =10 * -3.14 -> -31.4
A69: reference_driver (D') | B69: -
A70: scaling_factor (X) | B70: 1
A71: driver (D) | B71: -1
A72: type | B72: repeating
A73: period | B73: -
A74: taxable | B74: FALSE
A75: inflation | B75: none
A76: mult_target | B76: FALSE

Sheet SweepValue2
A1: CASE VARIABLES | B1: source capacity
A2: SWEEP VALUE | B2: 2
A4: END TIME | B4: 2
A5: NUM STEPS | B5: 21
A6: PROJECT TIME | B6: 20
A7: DISCOUNT RATE | B7: 0.08
A8: Inflation | B8: 0
A9: Tax | B9: 0.25
A11: YEAR 1
B12: Time | C12: 0 | D12: 0.1 | E12: 0.2 | F12: 0.3 | G12: 0.4 | H12: 0.5 | I12: 0.6 | J12: 0.7 | K12: 0.8 | L12: 0.9 | M12: 1 | N12: 1.1 | O12: 1.2 | P12: 1.3 | Q12: 1.4 | R12: 1.5 | S12: 1.6 | T12: 1.7 | U12: 1.8 | V12: 1.9 | W12: 2
B13: Signal | C13: -2.5120128e-10 | D13: 0.06279052 | E13: 0.12533323 | F13: 0.18738131 | G13: 0.24868989 | H13: 0.30901699 | I13: 0.36812455 | J13: 0.42577929 | K13: 0.48175367 | L13: 0.53582679 | M13: 0.58778525 | N13: 0.63742399 | O13: 0.68454711 | P13: 0.72896863 | Q13: 0.77051324 | R13: 0.80901699 | S13: 0.84432793 | T13: 0.87630668 | U13: 0.90482705 | V13: 0.92977649 | W13: 0.95105652
A15: SOURCE | B15: a | C15: =$B$2 -> 2 | D15: =$B$2 -> 2 | E15: =$B$2 -> 2 | F15: =$B$2 -> 2 | G15: =$B$2 -> 2 | H15: =$B$2 -> 2 | I15: =$B$2 -> 2 | J15: =$B$2 -> 2 | ... W15: =$B$2 -> 2
B16: CAPEX Price | C16: 0 | D16: 0 | E16: 0 | F16: 0 | G16: 0 | H16: 0 | I16: 0 | J16: 0 | K16: 0 | L16: 0 | M16: 0 | N16: 0 | O16: 0 | P16: 0 | Q16: 0 | R16: 0 | S16: 0 | T16: 0 | U16: 0 | V16: 0 | W16: 0
B17: CAPEX Cashflow | C17: =C16*(C15/$B$36)^$B$37 -> 0 | D17: =D16*(D15/$B$36)^$B$37 -> 0 | E17: =E16*(E15/$B$36)^$B$37 -> 0 | F17: =F16*(F15/$B$36)^$B$37 -> 0 | G17: =G16*(G15/$B$36)^$B$37 -> 0 | H17: =H16*(H15/$B$36)^$B$37 -> 0 | I17: =I16*(I15/$B$36)^$B$37 -> 0 | J17: =J16*(J15/$B$36)^$B$37 -> 0 | ... W17: =W16*(W15/$B$36)^$B$37 -> 0
B18: FOM Price | C18: =$B$47 -> -100 | D18: 0 | E18: 0 | F18: 0 | G18: 0 | H18: 0 | I18: 0 | J18: 0 | K18: 0 | L18: 0 | M18: 0 | N18: 0 | O18: 0 | P18: 0 | Q18: 0 | R18: 0 | S18: 0 | T18: 0 | U18: 0 | V18: 0 | W18: 0
B19: FOM Cashflow | C19: =C18*(C15/$B$48)^$B$49 -> -20.032215 | D19: =(D15*D16)+(D15*D17)+(D15*D18) -> 0 | E19: =(E15*E16)+(E15*E17)+(E15*E18) -> 0 | F19: =(F15*F16)+(F15*F17)+(F15*F18) -> 0 | G19: =(G15*G16)+(G15*G17)+(G15*G18) -> 0 | H19: =(H15*H16)+(H15*H17)+(H15*H18) -> 0 | I19: =(I15*I16)+(I15*I17)+(I15*I18) -> 0 | J19: =(J15*J16)+(J15*J17)+(J15*J18) -> 0 | K19: =(K15*K16)+(K15*K17)+(K15*K18) -> 0 | ... W19: =(W15*W16)+(W15*W17)+(W15*W18) -> 0
B20: VOM Price | C20: =$B$58 -> -1 | D20: =$B$58 -> -1 | E20: =$B$58 -> -1 | F20: =$B$58 -> -1 | G20: =$B$58 -> -1 | H20: =$B$58 -> -1 | I20: =$B$58 -> -1 | J20: =$B$58 -> -1 | ... W20: =$B$58 -> -1
B21: VOM Cashflow | C21: =(C20*(C15/1)^1)*(1-$B$9) -> -1.5 | D21: =(D20*(D15/1)^1)*(1-$B$9) -> -1.5 | E21: =(E20*(E15/1)^1)*(1-$B$9) -> -1.5 | F21: =(F20*(F15/1)^1)*(1-$B$9) -> -1.5 | G21: =(G20*(G15/1)^1)*(1-$B$9) -> -1.5 | H21: =(H20*(H15/1)^1)*(1-$B$9) -> -1.5 | I21: =(I20*(I15/1)^1)*(1-$B$9) -> -1.5 | J21: =(J20*(J15/1)^1)*(1-$B$9) -> -1.5 | ... W21: =(W20*(W15/1)^1)*(1-$B$9) -> -1.5 | X21: TOTAL
B22: TOTAL Cashflow | C22: =C21+C19+C17 -> -21.532215 | D22: =D21+D19+D17 -> -1.5 | E22: =E21+E19+E17 -> -1.5 | F22: =F21+F19+F17 -> -1.5 | G22: =G21+G19+G17 -> -1.5 | H22: =H21+H19+H17 -> -1.5 | I22: =I21+I19+I17 -> -1.5 | J22: =J21+J19+J17 -> -1.5 | ... W22: =W21+W19+W17 -> -1.5 | X22: =SUM(C22:W22) -> -51.532215
A24: SINK | B24: a | C24: =-$B$2 -> -2 | D24: =-$B$2 -> -2 | E24: =-$B$2 -> -2 | F24: =-$B$2 -> -2 | G24: =-$B$2 -> -2 | H24: =-$B$2 -> -2 | I24: =-$B$2 -> -2 | J24: =-$B$2 -> -2 | ... W24: =-$B$2 -> -2
B25: Sales Price | C25: =$B$69 -> -31.4 | D25: =10 * -3.14 -> -31.4 | E25: =10 * -3.14 -> -31.4 | F25: =10 * -3.14 -> -31.4 | G25: =10 * -3.14 -> -31.4 | H25: =10 * -3.14 -> -31.4 | I25: =10 * -3.14 -> -31.4 | J25: =10 * -3.14 -> -31.4 | K25: =10 * -3.14 -> -31.4 | ... W25: =10 * -3.14 -> -31.4 | X25: TOTAL
B26: Sales Cashflow | C26: =C25*(C24/1)^1 -> 62.8 | D26: =D25*(D24/1)^1 -> 62.8 | E26: =E25*(E24/1)^1 -> 62.8 | F26: =F25*(F24/1)^1 -> 62.8 | G26: =G25*(G24/1)^1 -> 62.8 | H26: =H25*(H24/1)^1 -> 62.8 | I26: =I25*(I24/1)^1 -> 62.8 | J26: =J25*(J24/1)^1 -> 62.8 | ... W26: =W25*(W24/1)^1 -> 62.8 | X26: =SUM(C26:W26) -> 1318.8
A28: HOURLY TOTAL | X28: TOTAL
B29: Cashflow | C29: =C26+C22 -> 41.267785 | D29: =D26+D22 -> 61.3 | E29: =E26+E22 -> 61.3 | F29: =F26+F22 -> 61.3 | G29: =G26+G22 -> 61.3 | H29: =H26+H22 -> 61.3 | I29: =I26+I22 -> 61.3 | J29: =J26+J22 -> 61.3 | ... W29: =W26+W22 -> 61.3 | X29: =SUM(C29:W29) -> 1267.2678
A33: These numbers are hardcoded from the given heron input file. Changing these values will effect final answer.
A34: CAPEX
A35: reference_price (a) | B35: -10000
A36: reference_driver (D') | B36: 10
A37: scaling_factor (X) | B37: 0.999
A38: driver (D) | B38: =B2 -> 2
A39: type | B39: one-time
A40: period | B40: -
A41: taxable | B41: FALSE
A42: inflation | B42: none
A43: mult_target | B43: FALSE
A44: depreciate | B44: 5
A46: FOM
A47: reference_price (a) | B47: -100
A48: reference_driver (D') | B48: 10
A49: scaling_factor (X) | B49: 0.999
A50: driver (D) | B50: =B2 -> 2
A51: type | B51: repeating
A52: period | B52: year
A53: taxable | B53: FALSE
A54: inflation | B54: none
A55: mult_target | B55: FALSE
A57: VOM
A58: reference_price (a) | B58: -1
A59: reference_driver (D') | B59: 1
A60: scaling_factor (X) | B60: 1
A61: driver (D) | B61: 1
A62: type | B62: repeating
A63: period | B63: -
A64: taxable | B64: TRUE
A65: inflation | B65: none
A66: mult_target | B66: FALSE
A68: Sales
A69: reference_price (a) | B69: =10 * -3.14 -> -31.4
A70: reference_driver (D') | B70: -
A71: scaling_factor (X) | B71: 1
A72: driver (D) | B72: -1
A73: type | B73: repeating
A74: period | B74: -
A75: taxable | B75: FALSE
A76: inflation | B76: none
A77: mult_target | B77: FALSE

Sheet ProjectCashflows
C1: CASE VARIABLES | D1: source capacity
C2: SweepValue1 | D2: 1
C3: SweepValue2 | D3: 2
C5: END TIME | D5: 2
C6: NUM STEPS | D6: 21
C7: PROJECT TIME | D7: 20
C8: DISCOUNT RATE | D8: 0.08
C9: Inflation | D9: 0
C10: Tax | D10: 0.25
C12: Source MACRS | D12: 0.15 | AJ12: YEARS | AL12: 0 | AM12: 1 | AN12: 2 | AO12: 3 | AP12: 4 | AQ12: 5 | AR12: 6 | AS12: 7 | AT12: 8 | AU12: 9 | AV12: 10 | AW12: 11 | AX12: 12 | AY12: 13 | AZ12: 14 | BA12: 15 | BB12: 16 | BC12: 17 | BD12: 18 | BE12: 19 | BF12: 20 | BG12: SUM | BR12: YEARS | BT12: 0 | BU12: 1 | BV12: 2 | BW12: 3 | BX12: 4 | BY12: 5 | BZ12: 6 | CA12: 7 | CB12: 8 | CC12: 9 | CD12: 10 | CE12: 11 | CF12: 12 | CG12: 13 | CH12: 14 | CI12: 15 | CJ12: 16 | CK12: 17 | CL12: 18 | CM12: 19 | CN12: 20 | CO12: SUM
C13: Source Lifetime | D13: 20 | AJ13: Tax Fraction | AL13: =1-$D$10 -> 0.75 | AM13: =1-$D$10 -> 0.75 | AN13: =1-$D$10 -> 0.75 | AO13: =1-$D$10 -> 0.75 | AP13: =1-$D$10 -> 0.75 | AQ13: =1-$D$10 -> 0.75 | AR13: =1-$D$10 -> 0.75 | AS13: =1-$D$10 -> 0.75 | ... BF13: =1-$D$10 -> 0.75 | BR13: Tax Fraction | BT13: =1-$D$10 -> 0.75 | BU13: =1-$D$10 -> 0.75 | BV13: =1-$D$10 -> 0.75 | BW13: =1-$D$10 -> 0.75 | BX13: =1-$D$10 -> 0.75 | BY13: =1-$D$10 -> 0.75 | BZ13: =1-$D$10 -> 0.75 | CA13: =1-$D$10 -> 0.75 | ... CN13: =1-$D$10 -> 0.75
AJ14: Discount Rate | AL14: =1/(1+$D$8)^AL12 -> 1 | AM14: =1/(1+$D$8)^AM12 -> 0.92592593 | AN14: =1/(1+$D$8)^AN12 -> 0.85733882 | AO14: =1/(1+$D$8)^AO12 -> 0.79383224 | AP14: =1/(1+$D$8)^AP12 -> 0.73502985 | AQ14: =1/(1+$D$8)^AQ12 -> 0.6805832 | AR14: =1/(1+$D$8)^AR12 -> 0.63016963 | AS14: =1/(1+$D$8)^AS12 -> 0.5834904 | ... BF14: =1/(1+$D$8)^BF12 -> 0.21454821 | BR14: Discount Rate | BT14: =1/(1+$D$8)^BT12 -> 1 | BU14: =1/(1+$D$8)^BU12 -> 0.92592593 | BV14: =1/(1+$D$8)^BV12 -> 0.85733882 | BW14: =1/(1+$D$8)^BW12 -> 0.79383224 | BX14: =1/(1+$D$8)^BX12 -> 0.73502985 | BY14: =1/(1+$D$8)^BY12 -> 0.6805832 | BZ14: =1/(1+$D$8)^BZ12 -> 0.63016963 | CA14: =1/(1+$D$8)^CA12 -> 0.5834904 | ... CN14: =1/(1+$D$8)^CN12 -> 0.21454821
C15: YEARS | E15: 0 | F15: 1 | G15: 2 | H15: 3 | I15: 4 | J15: 5 | K15: 6 | L15: 7 | M15: 8 | N15: 9 | O15: 10 | P15: 11 | Q15: 12 | R15: 13 | S15: 14 | T15: 15 | U15: 16 | V15: 17 | W15: 18 | X15: 19 | Y15: 20 | Z15: SUM | AJ15: MACRS Ammortization 15-Yr | AL15: 0 | AM15: 0 | AN15: 0 | AO15: 0 | AP15: 0 | AQ15: 0 | AR15: 0 | AS15: 0 | AT15: 0 | AU15: 0 | AV15: 0 | AW15: 0 | AX15: 0 | AY15: 0 | AZ15: 0 | BA15: 0 | BB15: 0 | BC15: 0 | BD15: 0 | BE15: 0 | BF15: 0 | BR15: MACRS Ammortization 15-Yr | BT15: 0 | BU15: 0 | BV15: 0 | BW15: 0 | BX15: 0 | BY15: 0 | BZ15: 0 | CA15: 0 | CB15: 0 | CC15: 0 | CD15: 0 | CE15: 0 | CF15: 0 | CG15: 0 | CH15: 0 | CI15: 0 | CJ15: 0 | CK15: 0 | CL15: 0 | CM15: 0 | CN15: 0
C16: Tax Fraction | E16: =1-$D$10 -> 0.75 | F16: =1-$D$10 -> 0.75 | G16: =1-$D$10 -> 0.75 | H16: =1-$D$10 -> 0.75 | I16: =1-$D$10 -> 0.75 | J16: =1-$D$10 -> 0.75 | K16: =1-$D$10 -> 0.75 | L16: =1-$D$10 -> 0.75 | ... Y16: =1-$D$10 -> 0.75
C17: Discount Rate | E17: =1/(1+$D$8)^E15 -> 1 | F17: =1/(1+$D$8)^F15 -> 0.92592593 | G17: =1/(1+$D$8)^G15 -> 0.85733882 | H17: =1/(1+$D$8)^H15 -> 0.79383224 | I17: =1/(1+$D$8)^I15 -> 0.73502985 | J17: =1/(1+$D$8)^J15 -> 0.6805832 | K17: =1/(1+$D$8)^K15 -> 0.63016963 | L17: =1/(1+$D$8)^L15 -> 0.5834904 | ... Y17: =1/(1+$D$8)^Y15 -> 0.21454821
C18: MACRS Ammortization 15-Yr | E18: 0 | F18: 0 | G18: 0 | H18: 0 | I18: 0 | J18: 0 | K18: 0 | L18: 0 | M18: 0 | N18: 0 | O18: 0 | P18: 0 | Q18: 0 | R18: 0 | S18: 0 | T18: 0 | U18: 0 | V18: 0 | W18: 0 | X18: 0 | Y18: 0 | AB18: StartTime=0
B19: SweepValue1 | C19: CAPEX | E19: =$D$86*($D$2/$D$87)^$D$88 -> -1002.3052 | F19: 0 | G19: 0 | H19: 0 | I19: 0 | J19: 0 | K19: 0 | L19: 0 | M19: 0 | N19: 0 | O19: 0 | P19: 0 | Q19: 0 | R19: 0 | S19: 0 | T19: 0 | U19: 0 | V19: 0 | W19: 0 | X19: 0 | Y19: 0 | AB19: CORRECT
C20: Summed Hourly Cashflow (already taxed) | E20: 0 | F20: =SweepValue1!$X$29*F17 -> 586.69162 | G20: =SweepValue1!$X$29*G17 -> 543.23298 | H20: =SweepValue1!$X$29*H17 -> 502.9935 | I20: =SweepValue1!$X$29*I17 -> 465.73472 | J20: =SweepValue1!$X$29*J17 -> 431.23585 | K20: =SweepValue1!$X$29*K17 -> 399.29246 | L20: =SweepValue1!$X$29*L17 -> 369.71524 | M20: =SweepValue1!$X$29*M17 -> 342.32892 | ... Y20: =SweepValue1!$X$29*Y17 -> 135.94353 | Z20: =SUM(E20:Y20) -> 6221.0428 | AA20: =SUM(Z20:Z23) -> 5469.3138
C21: CAPEX Cashflow | E21: =E19*E16 -> -751.72893 | F21: =F19*F16 -> 0 | G21: =G19*G16 -> 0 | H21: =H19*H16 -> 0 | I21: =I19*I16 -> 0 | J21: =J19*J16 -> 0 | K21: =K19*K16 -> 0 | L21: =L19*L16 -> 0 | ... Y21: =Y19*Y16 -> 0 | Z21: =SUM(E21:Y21) -> -751.72893
C22: Depreciation + | E22: =-$E$19*E17/100*E18 -> 0 | F22: =-$E$19*F17/100*F18 -> 0 | G22: =-$E$19*G17/100*G18 -> 0 | H22: =-$E$19*H17/100*H18 -> 0 | I22: =-$E$19*I17/100*I18 -> 0 | J22: =-$E$19*J17/100*J18 -> 0 | K22: =-$E$19*K17/100*K18 -> 0 | L22: =-$E$19*L17/100*L18 -> 0 | ... Y22: =-$E$19*Y17/100*Y18 -> 0 | Z22: =SUM(E22:Y22) -> 0
C23: Depreciation - | E23: =E18*E17/100*$E$21 -> 0 | F23: =F18*F17/100*$E$21 -> 0 | G23: =G18*G17/100*$E$21 -> 0 | H23: =H18*H17/100*$E$21 -> 0 | I23: =I18*I17/100*$E$21 -> 0 | J23: =J18*J17/100*$E$21 -> 0 | K23: =K18*K17/100*$E$21 -> 0 | L23: =L18*L17/100*$E$21 -> 0 | ... X23: =X18*X17/100*$E$21 -> 0 | Y23: =Y18*Y17*$E$21 -> 0 | Z23: =SUM(E23:Y23) -> 0
B24: SweepValue2 | C24: CAPEX | E24: =$D$86*($D$3/$D$87)^$D$88 -> -2003.2215 | F24: 0 | G24: 0 | H24: 0 | I24: 0 | J24: 0 | K24: 0 | L24: 0 | M24: 0 | N24: 0 | O24: 0 | P24: 0 | Q24: 0 | R24: 0 | S24: 0 | T24: 0 | U24: 0 | V24: 0 | W24: 0 | X24: 0 | Y24: 0
C25: Summed Hourly Cashflow (already taxed) | E25: 0 | F25: =SweepValue2!$X$29*F17 -> 1173.3961 | G25: =SweepValue2!$X$29*G17 -> 1086.4779 | H25: =SweepValue2!$X$29*H17 -> 1005.998 | I25: =SweepValue2!$X$29*I17 -> 931.47965 | J25: =SweepValue2!$X$29*J17 -> 862.48116 | K25: =SweepValue2!$X$29*K17 -> 798.59367 | L25: =SweepValue2!$X$29*L17 -> 739.43858 | M25: =SweepValue2!$X$29*M17 -> 684.66535 | ... Y25: =SweepValue2!$X$29*Y17 -> 271.89003 | Z25: =SUM(E25:Y25) -> 12442.222 | AA25: =SUM(Z25:Z28) -> 10939.806
C26: CAPEX Cashflow | E26: =E24*E16 -> -1502.4161 | F26: 0 | G26: 0 | H26: 0 | I26: 0 | J26: 0 | K26: 0 | L26: 0 | M26: 0 | N26: 0 | O26: 0 | P26: 0 | Q26: 0 | R26: 0 | S26: 0 | T26: 0 | U26: 0 | V26: 0 | W26: 0 | X26: 0 | Y26: 0 | Z26: =SUM(E26:Y26) -> -1502.4161
C27: Depreciation + | E27: =-$E$24*E17*E18/100 -> 0 | F27: =-$E$24*F17*F18/100 -> 0 | G27: =-$E$24*G17*G18/100 -> 0 | H27: =-$E$24*H17*H18/100 -> 0 | I27: =-$E$24*I17*I18/100 -> 0 | J27: =-$E$24*J17*J18/100 -> 0 | K27: =-$E$24*K17*K18/100 -> 0 | L27: =-$E$24*L17*L18/100 -> 0 | ... Y27: =-$E$24*Y17*Y18/100 -> 0 | Z27: =SUM(E27:Y27) -> 0
C28: Depreciation - | E28: =$E$26*E17*E18/100 -> 0 | F28: =$E$26*F17*F18/100 -> 0 | G28: =$E$26*G17*G18/100 -> 0 | H28: =$E$26*H17*H18/100 -> 0 | I28: =$E$26*I17*I18/100 -> 0 | J28: =$E$26*J17*J18/100 -> 0 | K28: =$E$26*K17*K18/100 -> 0 | L28: =$E$26*L17*L18/100 -> 0 | ... Y28: =$E$26*Y17*Y18/100 -> 0 | Z28: =SUM(E28:Y28) -> 0 | AJ28: StartTime + Lifetime < ProjectTime Lifetime > ProjectTime | BR28: StartTime + Lifetime > ProjectTime TEAL Errors Out
C32: Lifetime <= ProjectTime
BI34: Lifetime = 25 | CQ34: Lifetime = 40
AB35: StartTime=-5 | AJ35: YEARS | AL35: 0 | AM35: 1 | AN35: 2 | AO35: 3 | AP35: 4 | AQ35: 5 | AR35: 6 | AS35: 7 | AT35: 8 | AU35: 9 | AV35: 10 | AW35: 11 | AX35: 12 | AY35: 13 | AZ35: 14 | BA35: 15 | BB35: 16 | BC35: 17 | BD35: 18 | BE35: 19 | BF35: 20 | BI35: StartTime=-10 | BR35: YEARS | BT35: 0 | BU35: 1 | BV35: 2 | BW35: 3 | BX35: 4 | BY35: 5 | BZ35: 6 | CA35: 7 | CB35: 8 | CC35: 9 | CD35: 10 | CE35: 11 | CF35: 12 | CG35: 13 | CH35: 14 | CI35: 15 | CJ35: 16 | CK35: 17 | CL35: 18 | CM35: 19 | CN35: 20 | CQ35: StartTime=-5
B36: SweepValue1 | C36: CAPEX | E36: =$D$86*($D$2/$D$87)^$D$88 -> -1002.3052 | F36: 0 | G36: 0 | H36: 0 | I36: 0 | J36: 0 | K36: 0 | L36: 0 | M36: 0 | N36: 0 | O36: 0 | P36: 0 | Q36: 0 | R36: 0 | S36: 0 | T36: 0 | U36: 0 | V36: 0 | W36: 0 | X36: 0 | Y36: 0 | AB36: CORRECT | AI36: SweepValue1 | AJ36: CAPEX | AL36: =$D$86*($D$2/$D$87)^$D$88 -> -1002.3052 | AM36: 0 | AN36: 0 | AO36: 0 | AP36: 0 | AQ36: 0 | AR36: 0 | AS36: 0 | AT36: 0 | AU36: 0 | AV36: 0 | AW36: 0 | AX36: 0 | AY36: 0 | AZ36: 0 | BA36: 0 | BB36: 0 | BC36: 0 | BD36: 0 | BE36: 0 | BF36: 0 | BI36: CORRECT | BQ36: SweepValue1 | BR36: CAPEX | BT36: =$D$86*($D$2/$D$87)^$D$88 -> -1002.3052 | BU36: 0 | BV36: 0 | BW36: 0 | BX36: 0 | BY36: 0 | BZ36: 0 | CA36: 0 | CB36: 0 | CC36: 0 | CD36: 0 | CE36: 0 | CF36: 0 | CG36: 0 | CH36: 0 | CI36: 0 | CJ36: 0 | CK36: 0 | CL36: 0 | CM36: 0 | CN36: 0 | CQ36: ERROR
C37: Summed Hourly Cashflow (already taxed) | E37: 0 | F37: =F20 -> 586.69162 | G37: =G20 -> 543.23298 | H37: =H20 -> 502.9935 | I37: =I20 -> 465.73472 | J37: =J20 -> 431.23585 | K37: =K20 -> 399.29246 | L37: =L20 -> 369.71524 | M37: =M20 -> 342.32892 | ... Y37: =Y20 -> 135.94353 | Z37: =SUM(E37:Y37) -> 6221.0428 | AA37: =SUM(Z37:Z40) -> 5984.0665 | AJ37: Summed Hourly Cashflow (already taxed) | AL37: 0 | AM37: =F37 -> 586.69162 | AN37: =G37 -> 543.23298 | AO37: =H37 -> 502.9935 | AP37: =I37 -> 465.73472 | AQ37: =J37 -> 431.23585 | AR37: =K37 -> 399.29246 | AS37: =L37 -> 369.71524 | AT37: =M37 -> 342.32892 | ... BF37: =Y37 -> 135.94353 | BG37: =SUM(AL37:BF37) -> 6221.0428 | BH37: =SUM(BG37:BG40) -> 5984.0665 | BR37: Summed Hourly Cashflow (already taxed) | BT37: 0 | BU37: =AM37 -> 586.69162 | BV37: =AN37 -> 543.23298 | BW37: =AO37 -> 502.9935 | BX37: =AP37 -> 465.73472 | BY37: =AQ37 -> 431.23585 | BZ37: =AR37 -> 399.29246 | CA37: =AS37 -> 369.71524 | CB37: =AT37 -> 342.32892 | ... CN37: =BF37 -> 135.94353 | CO37: =SUM(BT37:CN37) -> 6221.0428 | CP37: =SUM(CO37:CO40) -> 6221.0428
C38: CAPEX Cashflow | E38: =E36*E31 -> 0 | F38: =F36*F31 -> 0 | G38: =G36*G31 -> 0 | H38: =H36*H31 -> 0 | I38: =I36*I31 -> 0 | J38: =J36*J31 -> 0 | K38: =K36*K31 -> 0 | L38: =L36*L31 -> 0 | ... S38: =S36*S31 -> 0 | T38: =E36*T16*T17 -> -236.97631 | U38: =U36*U31 -> 0 | V38: =V36*V31 -> 0 | W38: =W36*W31 -> 0 | X38: =X36*X31 -> 0 | Y38: =Y36*Y31 -> 0 | Z38: =SUM(E38:Y38) -> -236.97631 | AJ38: CAPEX Cashflow | AL38: =AL36*AL31 -> 0 | AM38: =AM36*AM31 -> 0 | AN38: =AN36*AN31 -> 0 | AO38: =AO36*AO31 -> 0 | AP38: =AP36*AP31 -> 0 | AQ38: =AQ36*AQ31 -> 0 | AR38: =AR36*AR31 -> 0 | AS38: =AS36*AS31 -> 0 | ... AZ38: =AZ36*AZ31 -> 0 | BA38: =AL36*BA13*BA14 -> -236.97631 | BB38: =BB36*BB31 -> 0 | BC38: =BC36*BC31 -> 0 | BD38: =BD36*BD31 -> 0 | BE38: =BE36*BE31 -> 0 | BF38: =BF36*BF31 -> 0 | BG38: =SUM(AL38:BF38) -> -236.97631 | BR38: CAPEX Cashflow | BT38: =BT36*BT31 -> 0 | BU38: =BU36*BU31 -> 0 | BV38: =BV36*BV31 -> 0 | BW38: =BW36*BW31 -> 0 | BX38: =BX36*BX31 -> 0 | BY38: =BY36*BY31 -> 0 | BZ38: =BZ36*BZ31 -> 0 | CA38: =CA36*CA31 -> 0 | ... CH38: =CH36*CH31 -> 0 | CI38: =BT36*CI16*CI17 -> 0 | CJ38: =CJ36*CJ31 -> 0 | CK38: =CK36*CK31 -> 0 | CL38: =CL36*CL31 -> 0 | CM38: =CM36*CM31 -> 0 | CN38: =CN36*CN31 -> 0 | CO38: =SUM(BT38:CN38) -> 0
C39: Depreciation + | E39: =-$E$19*E32/100*E35 -> 0 | F39: =-$E$19*F32/100*F35 -> 0 | G39: =-$E$19*G32/100*G35 -> 0 | H39: =-$E$19*H32/100*H35 -> 0 | I39: =-$E$19*I32/100*I35 -> 0 | J39: =-$E$19*J32/100*J35 -> 0 | K39: =-$E$19*K32/100*K35 -> 0 | L39: =-$E$19*L32/100*L35 -> 0 | ... Y39: =-$E$19*Y32/100*Y35 -> 0 | Z39: =SUM(E39:Y39) -> 0 | AJ39: Depreciation + | AL39: =-$E$19*AL32/100*AL35 -> 0 | AM39: =-$E$19*AM32/100*AM35 -> 0 | AN39: =-$E$19*AN32/100*AN35 -> 0 | AO39: =-$E$19*AO32/100*AO35 -> 0 | AP39: =-$E$19*AP32/100*AP35 -> 0 | AQ39: =-$E$19*AQ32/100*AQ35 -> 0 | AR39: =-$E$19*AR32/100*AR35 -> 0 | AS39: =-$E$19*AS32/100*AS35 -> 0 | ... BF39: =-$E$19*BF32/100*BF35 -> 0 | BG39: =SUM(AL39:BF39) -> 0 | BR39: Depreciation + | BT39: =-$E$19*BT32/100*BT35 -> 0 | BU39: =-$E$19*BU32/100*BU35 -> 0 | BV39: =-$E$19*BV32/100*BV35 -> 0 | BW39: =-$E$19*BW32/100*BW35 -> 0 | BX39: =-$E$19*BX32/100*BX35 -> 0 | BY39: =-$E$19*BY32/100*BY35 -> 0 | BZ39: =-$E$19*BZ32/100*BZ35 -> 0 | CA39: =-$E$19*CA32/100*CA35 -> 0 | ... CN39: =-$E$19*CN32/100*CN35 -> 0 | CO39: =SUM(BT39:CN39) -> 0
C40: Depreciation - | E40: =E35*E32/100*$E$21 -> 0 | F40: =F35*F32/100*$E$21 -> 0 | G40: =G35*G32/100*$E$21 -> 0 | H40: =H35*H32/100*$E$21 -> 0 | I40: =I35*I32/100*$E$21 -> 0 | J40: =J35*J32/100*$E$21 -> 0 | K40: =K35*K32/100*$E$21 -> 0 | L40: =L35*L32/100*$E$21 -> 0 | ... X40: =X35*X32/100*$E$21 -> 0 | Y40: =Y35*Y32*$E$21 -> 0 | Z40: =SUM(E40:Y40) -> 0 | AJ40: Depreciation - | AL40: =AL35*AL32/100*$E$21 -> 0 | AM40: =AM35*AM32/100*$E$21 -> 0 | AN40: =AN35*AN32/100*$E$21 -> 0 | AO40: =AO35*AO32/100*$E$21 -> 0 | AP40: =AP35*AP32/100*$E$21 -> 0 | AQ40: =AQ35*AQ32/100*$E$21 -> 0 | AR40: =AR35*AR32/100*$E$21 -> 0 | AS40: =AS35*AS32/100*$E$21 -> 0 | ... BE40: =BE35*BE32/100*$E$21 -> 0 | BF40: =BF35*BF32*$E$21 -> 0 | BG40: =SUM(AL40:BF40) -> 0 | BR40: Depreciation - | BT40: =BT35*BT32/100*$E$21 -> 0 | BU40: =BU35*BU32/100*$E$21 -> 0 | BV40: =BV35*BV32/100*$E$21 -> 0 | BW40: =BW35*BW32/100*$E$21 -> 0 | BX40: =BX35*BX32/100*$E$21 -> 0 | BY40: =BY35*BY32/100*$E$21 -> 0 | BZ40: =BZ35*BZ32/100*$E$21 -> 0 | CA40: =CA35*CA32/100*$E$21 -> 0 | ... CM40: =CM35*CM32/100*$E$21 -> 0 | CN40: =CN35*CN32*$E$21 -> 0 | CO40: =SUM(BT40:CN40) -> 0
B41: SweepValue2 | C41: CAPEX | E41: =$D$86*($D$3/$D$87)^$D$88 -> -2003.2215 | F41: 0 | G41: 0 | H41: 0 | I41: 0 | J41: 0 | K41: 0 | L41: 0 | M41: 0 | N41: 0 | O41: 0 | P41: 0 | Q41: 0 | R41: 0 | S41: 0 | T41: 0 | U41: 0 | V41: 0 | W41: 0 | X41: 0 | Y41: 0 | AI41: SweepValue2 | AJ41: CAPEX | AL41: =$D$86*($D$3/$D$87)^$D$88 -> -2003.2215 | AM41: 0 | AN41: 0 | AO41: 0 | AP41: 0 | AQ41: 0 | AR41: 0 | AS41: 0 | AT41: 0 | AU41: 0 | AV41: 0 | AW41: 0 | AX41: 0 | AY41: 0 | AZ41: 0 | BA41: 0 | BB41: 0 | BC41: 0 | BD41: 0 | BE41: 0 | BF41: 0 | BQ41: SweepValue2 | BR41: CAPEX | BT41: =$D$86*($D$3/$D$87)^$D$88 -> -2003.2215 | BU41: 0 | BV41: 0 | BW41: 0 | BX41: 0 | BY41: 0 | BZ41: 0 | CA41: 0 | CB41: 0 | CC41: 0 | CD41: 0 | CE41: 0 | CF41: 0 | CG41: 0 | CH41: 0 | CI41: 0 | CJ41: 0 | CK41: 0 | CL41: 0 | CM41: 0 | CN41: 0
C42: Summed Hourly Cashflow (already taxed) | E42: 0 | F42: =F25 -> 1173.3961 | G42: =G25 -> 1086.4779 | H42: =H25 -> 1005.998 | I42: =I25 -> 931.47965 | J42: =J25 -> 862.48116 | K42: =K25 -> 798.59367 | L42: =L25 -> 739.43858 | M42: =M25 -> 684.66535 | ... Y42: =Y25 -> 271.89003 | Z42: =SUM(E42:Y42) -> 12442.222 | AA42: =SUM(Z42:Z45) -> 11968.598 | AJ42: Summed Hourly Cashflow (already taxed) | AL42: 0 | AM42: =F42 -> 1173.3961 | AN42: =G42 -> 1086.4779 | AO42: =H42 -> 1005.998 | AP42: =I42 -> 931.47965 | AQ42: =J42 -> 862.48116 | AR42: =K42 -> 798.59367 | AS42: =L42 -> 739.43858 | AT42: =M42 -> 684.66535 | ... BF42: =Y42 -> 271.89003 | BG42: =SUM(AL42:BF42) -> 12442.222 | BH42: =SUM(BG42:BG45) -> 11968.598 | BR42: Summed Hourly Cashflow (already taxed) | BT42: 0 | BU42: =AM42 -> 1173.3961 | BV42: =AN42 -> 1086.4779 | BW42: =AO42 -> 1005.998 | BX42: =AP42 -> 931.47965 | BY42: =AQ42 -> 862.48116 | BZ42: =AR42 -> 798.59367 | CA42: =AS42 -> 739.43858 | CB42: =AT42 -> 684.66535 | ... CN42: =BF42 -> 271.89003 | CO42: =SUM(BT42:CN42) -> 12442.222 | CP42: =SUM(CO42:CO45) -> 12442.222
C43: CAPEX Cashflow | E43: =E41*E31 -> 0 | F43: 0 | G43: 0 | H43: 0 | I43: 0 | J43: 0 | K43: 0 | L43: 0 | M43: 0 | N43: 0 | O43: 0 | P43: 0 | Q43: 0 | R43: 0 | S43: 0 | T43: =E41*T16*T17 -> -473.62421 | U43: 0 | V43: 0 | W43: 0 | X43: 0 | Y43: 0 | Z43: =SUM(E43:Y43) -> -473.62421 | AJ43: CAPEX Cashflow | AL43: =AL41*AL31 -> 0 | AM43: 0 | AN43: 0 | AO43: 0 | AP43: 0 | AQ43: 0 | AR43: 0 | AS43: 0 | AT43: 0 | AU43: 0 | AV43: 0 | AW43: 0 | AX43: 0 | AY43: 0 | AZ43: 0 | BA43: =AL41*BA13*BA14 -> -473.62421 | BB43: 0 | BC43: 0 | BD43: 0 | BE43: 0 | BF43: 0 | BG43: =SUM(AL43:BF43) -> -473.62421 | BR43: CAPEX Cashflow | BT43: =BT41*BT31 -> 0 | BU43: 0 | BV43: 0 | BW43: 0 | BX43: 0 | BY43: 0 | BZ43: 0 | CA43: 0 | CB43: 0 | CC43: 0 | CD43: 0 | CE43: 0 | CF43: 0 | CG43: 0 | CH43: 0 | CI43: =BT41*CI16*CI17 -> 0 | CJ43: 0 | CK43: 0 | CL43: 0 | CM43: 0 | CN43: 0 | CO43: =SUM(BT43:CN43) -> 0
C44: Depreciation + | E44: =-$E$24*E32*E35/100 -> 0 | F44: =-$E$24*F32*F35/100 -> 0 | G44: =-$E$24*G32*G35/100 -> 0 | H44: =-$E$24*H32*H35/100 -> 0 | I44: =-$E$24*I32*I35/100 -> 0 | J44: =-$E$24*J32*J35/100 -> 0 | K44: =-$E$24*K32*K35/100 -> 0 | L44: =-$E$24*L32*L35/100 -> 0 | ... Y44: =-$E$24*Y32*Y35/100 -> 0 | Z44: =SUM(E44:Y44) -> 0 | AJ44: Depreciation + | AL44: =-$E$24*AL32*AL35/100 -> 0 | AM44: =-$E$24*AM32*AM35/100 -> 0 | AN44: =-$E$24*AN32*AN35/100 -> 0 | AO44: =-$E$24*AO32*AO35/100 -> 0 | AP44: =-$E$24*AP32*AP35/100 -> 0 | AQ44: =-$E$24*AQ32*AQ35/100 -> 0 | AR44: =-$E$24*AR32*AR35/100 -> 0 | AS44: =-$E$24*AS32*AS35/100 -> 0 | ... BF44: =-$E$24*BF32*BF35/100 -> 0 | BG44: =SUM(AL44:BF44) -> 0 | BR44: Depreciation + | BT44: =-$E$24*BT32*BT35/100 -> 0 | BU44: =-$E$24*BU32*BU35/100 -> 0 | BV44: =-$E$24*BV32*BV35/100 -> 0 | BW44: =-$E$24*BW32*BW35/100 -> 0 | BX44: =-$E$24*BX32*BX35/100 -> 0 | BY44: =-$E$24*BY32*BY35/100 -> 0 | BZ44: =-$E$24*BZ32*BZ35/100 -> 0 | CA44: =-$E$24*CA32*CA35/100 -> 0 | ... CN44: =-$E$24*CN32*CN35/100 -> 0 | CO44: =SUM(BT44:CN44) -> 0
C45: Depreciation - | E45: =$E$26*E32*E35/100 -> 0 | F45: =$E$26*F32*F35/100 -> 0 | G45: =$E$26*G32*G35/100 -> 0 | H45: =$E$26*H32*H35/100 -> 0 | I45: =$E$26*I32*I35/100 -> 0 | J45: =$E$26*J32*J35/100 -> 0 | K45: =$E$26*K32*K35/100 -> 0 | L45: =$E$26*L32*L35/100 -> 0 | ... Y45: =$E$26*Y32*Y35/100 -> 0 | Z45: =SUM(E45:Y45) -> 0 | AJ45: Depreciation - | AL45: =$E$26*AL32*AL35/100 -> 0 | AM45: =$E$26*AM32*AM35/100 -> 0 | AN45: =$E$26*AN32*AN35/100 -> 0 | AO45: =$E$26*AO32*AO35/100 -> 0 | AP45: =$E$26*AP32*AP35/100 -> 0 | AQ45: =$E$26*AQ32*AQ35/100 -> 0 | AR45: =$E$26*AR32*AR35/100 -> 0 | AS45: =$E$26*AS32*AS35/100 -> 0 | ... BF45: =$E$26*BF32*BF35/100 -> 0 | BG45: =SUM(AL45:BF45) -> 0 | BR45: Depreciation - | BT45: =$E$26*BT32*BT35/100 -> 0 | BU45: =$E$26*BU32*BU35/100 -> 0 | BV45: =$E$26*BV32*BV35/100 -> 0 | BW45: =$E$26*BW32*BW35/100 -> 0 | BX45: =$E$26*BX32*BX35/100 -> 0 | BY45: =$E$26*BY32*BY35/100 -> 0 | BZ45: =$E$26*BZ32*BZ35/100 -> 0 | CA45: =$E$26*CA32*CA35/100 -> 0 | ... CN45: =$E$26*CN32*CN35/100 -> 0 | CO45: =SUM(BT45:CN45) -> 0
AB47: StartTime=-12.5
B48: SweepValue1 | C48: CAPEX | E48: =$D$86*($D$2/$D$87)^$D$88 -> -1002.3052 | F48: 0 | G48: 0 | H48: 0 | I48: 0 | J48: 0 | K48: 0 | L48: 0 | M48: 0 | N48: 0 | O48: 0 | P48: 0 | Q48: 0 | R48: 0 | S48: 0 | T48: 0 | U48: 0 | V48: 0 | W48: 0 | X48: 0 | Y48: 0 | AB48: CORRECT
C49: Summed Hourly Cashflow (already taxed) | E49: 0 | F49: =F37 -> 586.69162 | G49: =G37 -> 543.23298 | H49: =H37 -> 502.9935 | I49: =I37 -> 465.73472 | J49: =J37 -> 431.23585 | K49: =K37 -> 399.29246 | L49: =L37 -> 369.71524 | M49: =M37 -> 342.32892 | ... Y49: =Y37 -> 135.94353 | Z49: =SUM(E49:Y49) -> 6221.0428 | AA49: =SUM(Z49:Z52) -> 5814.907
C50: CAPEX Cashflow | E50: 0 | F50: 0 | G50: 0 | H50: 0 | I50: 0 | J50: 0 | K50: 0 | L50: 0 | M50: =$E$48*M16*M17 -> -406.13575 | N50: 0 | O50: 0 | P50: 0 | Q50: 0 | R50: 0 | S50: 0 | T50: 0 | U50: 0 | V50: 0 | W50: 0 | X50: 0 | Y50: 0 | Z50: =SUM(E50:Y50) -> -406.13575
C51: Depreciation + | E51: =-$E$19*E46/100*E47 -> 0 | F51: =-$E$19*F46/100*F47 -> 0 | G51: =-$E$19*G46/100*G47 -> 0 | H51: =-$E$19*H46/100*H47 -> 0 | I51: =-$E$19*I46/100*I47 -> 0 | J51: =-$E$19*J46/100*J47 -> 0 | K51: =-$E$19*K46/100*K47 -> 0 | L51: =-$E$19*L46/100*L47 -> 0 | ... Y51: =-$E$19*Y46/100*Y47 -> 0 | Z51: =SUM(E51:Y51) -> 0
C52: Depreciation - | E52: =E47*E46/100*$E$21 -> 0 | F52: =F47*F46/100*$E$21 -> 0 | G52: =G47*G46/100*$E$21 -> 0 | H52: =H47*H46/100*$E$21 -> 0 | I52: =I47*I46/100*$E$21 -> 0 | J52: =J47*J46/100*$E$21 -> 0 | K52: =K47*K46/100*$E$21 -> 0 | L52: =L47*L46/100*$E$21 -> 0 | ... X52: =X47*X46/100*$E$21 -> 0 | Y52: =Y47*Y46*$E$21 -> 0 | Z52: =SUM(E52:Y52) -> 0
B53: SweepValue2 | C53: CAPEX | E53: =$D$86*($D$3/$D$87)^$D$88 -> -2003.2215 | F53: 0 | G53: 0 | H53: 0 | I53: 0 | J53: 0 | K53: 0 | L53: 0 | M53: 0 | N53: 0 | O53: 0 | P53: 0 | Q53: 0 | R53: 0 | S53: 0 | T53: 0 | U53: 0 | V53: 0 | W53: 0 | X53: 0 | Y53: 0
C54: Summed Hourly Cashflow (already taxed) | E54: 0 | F54: =F42 -> 1173.3961 | G54: =G42 -> 1086.4779 | H54: =H42 -> 1005.998 | I54: =I42 -> 931.47965 | J54: =J42 -> 862.48116 | K54: =K42 -> 798.59367 | L54: =L42 -> 739.43858 | M54: =M42 -> 684.66535 | ... Y54: =Y42 -> 271.89003 | Z54: =SUM(E54:Y54) -> 12442.222 | AA54: =SUM(Z54:Z57) -> 11630.513
C55: CAPEX Cashflow | E55: 0 | F55: 0 | G55: 0 | H55: 0 | I55: 0 | J55: 0 | K55: 0 | L55: 0 | M55: =$E$53*M16*M17 -> -811.70867 | N55: 0 | O55: 0 | P55: 0 | Q55: 0 | R55: 0 | S55: 0 | T55: =E53*T29*T30 -> 0 | U55: 0 | V55: 0 | W55: 0 | X55: 0 | Y55: 0 | Z55: =SUM(E55:Y55) -> -811.70867
C56: Depreciation + | E56: =-$E$24*E46*E47/100 -> 0 | F56: =-$E$24*F46*F47/100 -> 0 | G56: =-$E$24*G46*G47/100 -> 0 | H56: =-$E$24*H46*H47/100 -> 0 | I56: =-$E$24*I46*I47/100 -> 0 | J56: =-$E$24*J46*J47/100 -> 0 | K56: =-$E$24*K46*K47/100 -> 0 | L56: =-$E$24*L46*L47/100 -> 0 | ... Y56: =-$E$24*Y46*Y47/100 -> 0 | Z56: =SUM(E56:Y56) -> 0
C57: Depreciation - | E57: =$E$26*E46*E47/100 -> 0 | F57: =$E$26*F46*F47/100 -> 0 | G57: =$E$26*G46*G47/100 -> 0 | H57: =$E$26*H46*H47/100 -> 0 | I57: =$E$26*I46*I47/100 -> 0 | J57: =$E$26*J46*J47/100 -> 0 | K57: =$E$26*K46*K47/100 -> 0 | L57: =$E$26*L46*L47/100 -> 0 | ... Y57: =$E$26*Y46*Y47/100 -> 0 | Z57: =SUM(E57:Y57) -> 0
AB59: StartTime=-20
B60: SweepValue1 | C60: CAPEX | E60: =$D$86*($D$2/$D$87)^$D$88 -> -1002.3052 | F60: 0 | G60: 0 | H60: 0 | I60: 0 | J60: 0 | K60: 0 | L60: 0 | M60: 0 | N60: 0 | O60: 0 | P60: 0 | Q60: 0 | R60: 0 | S60: 0 | T60: 0 | U60: 0 | V60: 0 | W60: 0 | X60: 0 | Y60: 0 | AB60: CORRECT | AC60: If StartTime == - LifeTime results are the same as if StartTime = 0
C61: Summed Hourly Cashflow (already taxed) | E61: 0 | F61: =F37 -> 586.69162 | G61: =G37 -> 543.23298 | H61: =H37 -> 502.9935 | I61: =I37 -> 465.73472 | J61: =J37 -> 431.23585 | K61: =K37 -> 399.29246 | L61: =L37 -> 369.71524 | M61: =M37 -> 342.32892 | ... Y61: =Y37 -> 135.94353 | Z61: =SUM(E61:Y61) -> 6221.0428 | AA61: =SUM(Z61:Z64) -> 5469.3138
C62: CAPEX Cashflow | E62: =E60*E16 -> -751.72893 | F62: 0 | G62: =G60*G56 -> 0 | H62: =H60*H56 -> 0 | I62: =I60*I56 -> 0 | J62: =J60*J56 -> 0 | K62: =K60*K56 -> 0 | L62: 0 | M62: =$E$48*M28*M29 -> 0 | N62: =N60*N56 -> 0 | O62: =O60*O56 -> 0 | P62: =P60*P56 -> 0 | Q62: =Q60*Q56 -> 0 | R62: =R60*R56 -> 0 | S62: =S60*S56 -> 0 | T62: =E60*T43*T44 -> 0 | U62: =U60*U56 -> 0 | V62: =V60*V56 -> 0 | W62: =W60*W56 -> 0 | X62: =X60*X56 -> 0 | Y62: =Y60*Y56 -> 0 | Z62: =SUM(E62:Y62) -> -751.72893
C63: Depreciation + | E63: =-$E$19*E58/100*E59 -> 0 | F63: =-$E$19*F58/100*F59 -> 0 | G63: =-$E$19*G58/100*G59 -> 0 | H63: =-$E$19*H58/100*H59 -> 0 | I63: =-$E$19*I58/100*I59 -> 0 | J63: =-$E$19*J58/100*J59 -> 0 | K63: =-$E$19*K58/100*K59 -> 0 | L63: =-$E$19*L58/100*L59 -> 0 | ... Y63: =-$E$19*Y58/100*Y59 -> 0 | Z63: =SUM(E63:Y63) -> 0
C64: Depreciation - | E64: =E59*E58/100*$E$21 -> 0 | F64: =F59*F58/100*$E$21 -> 0 | G64: =G59*G58/100*$E$21 -> 0 | H64: =H59*H58/100*$E$21 -> 0 | I64: =I59*I58/100*$E$21 -> 0 | J64: =J59*J58/100*$E$21 -> 0 | K64: =K59*K58/100*$E$21 -> 0 | L64: =L59*L58/100*$E$21 -> 0 | ... X64: =X59*X58/100*$E$21 -> 0 | Y64: =Y59*Y58*$E$21 -> 0 | Z64: =SUM(E64:Y64) -> 0
B65: SweepValue2 | C65: CAPEX | E65: =$D$86*($D$3/$D$87)^$D$88 -> -2003.2215 | F65: 0 | G65: 0 | H65: 0 | I65: 0 | J65: 0 | K65: 0 | L65: 0 | M65: 0 | N65: 0 | O65: 0 | P65: 0 | Q65: 0 | R65: 0 | S65: 0 | T65: 0 | U65: 0 | V65: 0 | W65: 0 | X65: 0 | Y65: 0
C66: Summed Hourly Cashflow (already taxed) | E66: 0 | F66: =F54 -> 1173.3961 | G66: =G54 -> 1086.4779 | H66: =H54 -> 1005.998 | I66: =I54 -> 931.47965 | J66: =J54 -> 862.48116 | K66: =K54 -> 798.59367 | L66: =L54 -> 739.43858 | M66: =M54 -> 684.66535 | ... Y66: =Y54 -> 271.89003 | Z66: =SUM(E66:Y66) -> 12442.222 | AA66: =SUM(Z66:Z69) -> 10939.806
C67: CAPEX Cashflow | E67: =E65*E16 -> -1502.4161 | F67: 0 | G67: 0 | H67: 0 | I67: 0 | J67: 0 | K67: 0 | L67: 0 | M67: =$E$53*M28*M29 -> 0 | N67: 0 | O67: 0 | P67: 0 | Q67: 0 | R67: 0 | S67: 0 | T67: =E65*T43*T44 -> 0 | U67: 0 | V67: 0 | W67: 0 | X67: 0 | Y67: 0 | Z67: =SUM(E67:Y67) -> -1502.4161
C68: Depreciation + | E68: =-$E$24*E58*E59/100 -> 0 | F68: =-$E$24*F58*F59/100 -> 0 | G68: =-$E$24*G58*G59/100 -> 0 | H68: =-$E$24*H58*H59/100 -> 0 | I68: =-$E$24*I58*I59/100 -> 0 | J68: =-$E$24*J58*J59/100 -> 0 | K68: =-$E$24*K58*K59/100 -> 0 | L68: =-$E$24*L58*L59/100 -> 0 | ... Y68: =-$E$24*Y58*Y59/100 -> 0 | Z68: =SUM(E68:Y68) -> 0
C69: Depreciation - | E69: =$E$26*E58*E59/100 -> 0 | F69: =$E$26*F58*F59/100 -> 0 | G69: =$E$26*G58*G59/100 -> 0 | H69: =$E$26*H58*H59/100 -> 0 | I69: =$E$26*I58*I59/100 -> 0 | J69: =$E$26*J58*J59/100 -> 0 | K69: =$E$26*K58*K59/100 -> 0 | L69: =$E$26*L58*L59/100 -> 0 | ... Y69: =$E$26*Y58*Y59/100 -> 0 | Z69: =SUM(E69:Y69) -> 0
AB71: StartTime=-25
B72: SweepValue1 | C72: CAPEX | E72: =$D$86*($D$2/$D$87)^$D$88 -> -1002.3052 | F72: 0 | G72: 0 | H72: 0 | I72: 0 | J72: 0 | K72: 0 | L72: 0 | M72: 0 | N72: 0 | O72: 0 | P72: 0 | Q72: 0 | R72: 0 | S72: 0 | T72: 0 | U72: 0 | V72: 0 | W72: 0 | X72: 0 | Y72: 0 | AB72: CORRECT | AC72: If StartTime == -(LifeTime+dt) results are the same as if StartTime = -dt
C73: Summed Hourly Cashflow (already taxed) | E73: 0 | F73: =F61 -> 586.69162 | G73: =G61 -> 543.23298 | H73: =H61 -> 502.9935 | I73: =I61 -> 465.73472 | J73: =J61 -> 431.23585 | K73: =K61 -> 399.29246 | L73: =L61 -> 369.71524 | M73: =M61 -> 342.32892 | ... Y73: =Y61 -> 135.94353 | Z73: =SUM(E73:Y73) -> 6221.0428 | AA73: =SUM(Z73:Z76) -> 5984.0665
C74: CAPEX Cashflow | E74: 0 | F74: =F72*F67 -> 0 | G74: =G72*G67 -> 0 | H74: =H72*H67 -> 0 | I74: =I72*I67 -> 0 | J74: =J72*J67 -> 0 | K74: =K72*K67 -> 0 | L74: =L72*L67 -> 0 | M74: =M72*M67 -> 0 | ... S74: =S72*S67 -> 0 | T74: =T38 -> -236.97631 | U74: =U72*U67 -> 0 | V74: =V72*V67 -> 0 | W74: =W72*W67 -> 0 | X74: =X72*X67 -> 0 | Y74: =Y72*Y67 -> 0 | Z74: =SUM(E74:Y74) -> -236.97631
C75: Depreciation + | E75: =-$E$19*E68/100*E71 -> 0 | F75: =-$E$19*F68/100*F71 -> 0 | G75: =-$E$19*G68/100*G71 -> 0 | H75: =-$E$19*H68/100*H71 -> 0 | I75: =-$E$19*I68/100*I71 -> 0 | J75: =-$E$19*J68/100*J71 -> 0 | K75: =-$E$19*K68/100*K71 -> 0 | L75: =-$E$19*L68/100*L71 -> 0 | ... Y75: =-$E$19*Y68/100*Y71 -> 0 | Z75: =SUM(E75:Y75) -> 0
C76: Depreciation - | E76: =E71*E68/100*$E$21 -> 0 | F76: =F71*F68/100*$E$21 -> 0 | G76: =G71*G68/100*$E$21 -> 0 | H76: =H71*H68/100*$E$21 -> 0 | I76: =I71*I68/100*$E$21 -> 0 | J76: =J71*J68/100*$E$21 -> 0 | K76: =K71*K68/100*$E$21 -> 0 | L76: =L71*L68/100*$E$21 -> 0 | ... X76: =X71*X68/100*$E$21 -> 0 | Y76: =Y71*Y68*$E$21 -> 0 | Z76: =SUM(E76:Y76) -> 0
B77: SweepValue2 | C77: CAPEX | E77: =$D$86*($D$3/$D$87)^$D$88 -> -2003.2215 | F77: 0 | G77: 0 | H77: 0 | I77: 0 | J77: 0 | K77: 0 | L77: 0 | M77: 0 | N77: 0 | O77: 0 | P77: 0 | Q77: 0 | R77: 0 | S77: 0 | T77: 0 | U77: 0 | V77: 0 | W77: 0 | X77: 0 | Y77: 0
C78: Summed Hourly Cashflow (already taxed) | E78: 0 | F78: =F66 -> 1173.3961 | G78: =G66 -> 1086.4779 | H78: =H66 -> 1005.998 | I78: =I66 -> 931.47965 | J78: =J66 -> 862.48116 | K78: =K66 -> 798.59367 | L78: =L66 -> 739.43858 | M78: =M66 -> 684.66535 | ... Y78: =Y66 -> 271.89003 | Z78: =SUM(E78:Y78) -> 12442.222 | AA78: =SUM(Z78:Z81) -> 11968.598
C79: CAPEX Cashflow | E79: 0 | F79: 0 | G79: 0 | H79: 0 | I79: 0 | J79: 0 | K79: 0 | L79: 0 | M79: 0 | N79: 0 | O79: 0 | P79: 0 | Q79: 0 | R79: 0 | S79: 0 | T79: =T43 -> -473.62421 | U79: 0 | V79: 0 | W79: 0 | X79: 0 | Y79: 0 | Z79: =SUM(E79:Y79) -> -473.62421
C80: Depreciation + | E80: =-$E$24*E68*E71/100 -> 0 | F80: =-$E$24*F68*F71/100 -> 0 | G80: =-$E$24*G68*G71/100 -> 0 | H80: =-$E$24*H68*H71/100 -> 0 | I80: =-$E$24*I68*I71/100 -> 0 | J80: =-$E$24*J68*J71/100 -> 0 | K80: =-$E$24*K68*K71/100 -> 0 | L80: =-$E$24*L68*L71/100 -> 0 | ... Y80: =-$E$24*Y68*Y71/100 -> 0 | Z80: =SUM(E80:Y80) -> 0
C81: Depreciation - | E81: =$E$26*E68*E71/100 -> 0 | F81: =$E$26*F68*F71/100 -> 0 | G81: =$E$26*G68*G71/100 -> 0 | H81: =$E$26*H68*H71/100 -> 0 | I81: =$E$26*I68*I71/100 -> 0 | J81: =$E$26*J68*J71/100 -> 0 | K81: =$E$26*K68*K71/100 -> 0 | L81: =$E$26*L68*L71/100 -> 0 | ... Y81: =$E$26*Y68*Y71/100 -> 0 | Z81: =SUM(E81:Y81) -> 0
C84: These numbers are hardcoded from the given heron input file. Changing these values will affect final answer.
C85: CAPEX
C86: reference_price (a) | D86: -10000
C87: reference_driver (D') | D87: 10
C88: scaling_factor (X) | D88: 0.999
C89: driver (D) | D89: =D2 -> 1
C90: type | D90: one-time
C91: period | D91: -
C92: taxable | D92: TRUE
C93: inflation | D93: none
C94: mult_target | D94: FALSE
C95: depreciate | D95: 5
C97: FOM
C98: reference_price (a) | D98: -100
C99: reference_driver (D') | D99: 10
C100: scaling_factor (X) | D100: 0.999
C101: driver (D) | D101: =D89 -> 1
C102: type | D102: repeating
C103: period | D103: year
C104: taxable | D104: FALSE
C105: inflation | D105: none
C106: mult_target | D106: FALSE
C108: VOM
C109: reference_price (a) | D109: -1
C110: reference_driver (D') | D110: 1
C111: scaling_factor (X) | D111: 1
C112: driver (D) | D112: 1
C113: type | D113: repeating
...

Sheet ProjectCashflows - Depreciate
C1: CASE VARIABLES | D1: source capacity
C2: SweepValue1 | D2: 1
C3: SweepValue2 | D3: 2
C5: END TIME | D5: 2
C6: NUM STEPS | D6: 21
C7: PROJECT TIME | D7: 20
C8: DISCOUNT RATE | D8: 0.08
C9: Inflation | D9: 0
C10: Tax | D10: 0.25
C12: Source MACRS | D12: 7
C13: Source Lifetime | D13: 20
C15: PROJECT YEARS | E15: 0 | F15: 1 | G15: 2 | H15: 3 | I15: 4 | J15: 5 | K15: 6 | L15: 7 | M15: 8 | N15: 9 | O15: 10 | P15: 11 | Q15: 12 | R15: 13 | S15: 14 | T15: 15 | U15: 16 | V15: 17 | W15: 18 | X15: 19 | Y15: 20 | Z15: SUM | BR15: PROJECT YEARS | BT15: 0 | BU15: 1 | BV15: 2 | BW15: 3 | BX15: 4 | BY15: 5 | BZ15: 6 | CA15: 7 | CB15: 8 | CC15: 9 | CD15: 10 | CE15: 11 | CF15: 12 | CG15: 13 | CH15: 14 | CI15: 15 | CJ15: 16 | CK15: 17 | CL15: 18 | CM15: 19 | CN15: 20
C16: Tax Fraction | E16: =1-$D$10 -> 0.75 | F16: =1-$D$10 -> 0.75 | G16: =1-$D$10 -> 0.75 | H16: =1-$D$10 -> 0.75 | I16: =1-$D$10 -> 0.75 | J16: =1-$D$10 -> 0.75 | K16: =1-$D$10 -> 0.75 | L16: =1-$D$10 -> 0.75 | ... Y16: =1-$D$10 -> 0.75 | BR16: Tax Fraction | BT16: =1-$D$10 -> 0.75 | BU16: =1-$D$10 -> 0.75 | BV16: =1-$D$10 -> 0.75 | BW16: =1-$D$10 -> 0.75 | BX16: =1-$D$10 -> 0.75 | BY16: =1-$D$10 -> 0.75 | BZ16: =1-$D$10 -> 0.75 | CA16: =1-$D$10 -> 0.75 | ... CN16: =1-$D$10 -> 0.75
C17: Discount Rate | E17: =1/(1+$D$8)^E15 -> 1 | F17: =1/(1+$D$8)^F15 -> 0.92592593 | G17: =1/(1+$D$8)^G15 -> 0.85733882 | H17: =1/(1+$D$8)^H15 -> 0.79383224 | I17: =1/(1+$D$8)^I15 -> 0.73502985 | J17: =1/(1+$D$8)^J15 -> 0.6805832 | K17: =1/(1+$D$8)^K15 -> 0.63016963 | L17: =1/(1+$D$8)^L15 -> 0.5834904 | ... Y17: =1/(1+$D$8)^Y15 -> 0.21454821 | BR17: Discount Rate | BT17: =1/(1+$D$8)^BT15 -> 1 | BU17: =1/(1+$D$8)^BU15 -> 0.92592593 | BV17: =1/(1+$D$8)^BV15 -> 0.85733882 | BW17: =1/(1+$D$8)^BW15 -> 0.79383224 | BX17: =1/(1+$D$8)^BX15 -> 0.73502985 | BY17: =1/(1+$D$8)^BY15 -> 0.6805832 | BZ17: =1/(1+$D$8)^BZ15 -> 0.63016963 | CA17: =1/(1+$D$8)^CA15 -> 0.5834904 | ... CN17: =1/(1+$D$8)^CN15 -> 0.21454821
C18: MACRS Ammortization 7-Yr % | E18: 0 | F18: 14.29 | G18: 24.49 | H18: 17.49 | I18: 12.49 | J18: 8.93 | K18: 8.92 | L18: 8.93 | M18: 4.46 | N18: 0 | O18: 0 | P18: 0 | Q18: 0 | R18: 0 | S18: 0 | T18: 0 | U18: 0 | V18: 0 | W18: 0 | X18: 0 | Y18: 0 | BQ18: 7 | BR18: MACRS Ammortization 7-Yr % | BT18: 0 | BU18: 14.29 | BV18: 24.49 | BW18: 17.49 | BX18: 12.49 | BY18: 8.93 | BZ18: 8.92 | CA18: 8.93 | CB18: 4.46 | CC18: 0 | CD18: 0 | CE18: 0 | CF18: 0 | CG18: 0 | CH18: 0 | CI18: 0 | CJ18: 0 | CK18: 0 | CL18: 0 | CM18: 0 | CN18: 0
C19: MACRS Coefficient | E19: =E18/100 -> 0 | F19: =F18/100 -> 0.1429 | G19: =G18/100 -> 0.2449 | H19: =H18/100 -> 0.1749 | I19: =I18/100 -> 0.1249 | J19: =J18/100 -> 0.0893 | K19: =K18/100 -> 0.0892 | L19: =L18/100 -> 0.0893 | ... Y19: =Y18/100 -> 0 | AB19: StartTime=0 | BR19: MACRS Coefficient (7yr) | BT19: =BT18/100 -> 0 | BU19: =BU18/100 -> 0.1429 | BV19: =BV18/100 -> 0.2449 | BW19: =BW18/100 -> 0.1749 | BX19: =BX18/100 -> 0.1249 | BY19: =BY18/100 -> 0.0893 | BZ19: =BZ18/100 -> 0.0892 | CA19: =CA18/100 -> 0.0893 | ... CN19: =CN18/100 -> 0
B20: SweepValue1 | C20: CAPEX | E20: =$D$109*($D$2/$D$110)^$D$111 -> -1002.3052 | F20: 0 | G20: 0 | H20: 0 | I20: 0 | J20: 0 | K20: 0 | L20: 0 | M20: 0 | N20: 0 | O20: 0 | P20: 0 | Q20: 0 | R20: 0 | S20: 0 | T20: 0 | U20: 0 | V20: 0 | W20: 0 | X20: 0 | Y20: 0 | AB20: CORRECT | BQ20: 15 | BR20: MACRS Ammortization 15-Yr % | BT20: 0 | BU20: 5 | BV20: 9.5 | BW20: 8.55 | BX20: 7.7 | BY20: 6.93 | BZ20: 6.23 | CA20: 5.9 | CB20: 5.9 | CC20: 5.91 | CD20: 5.9 | CE20: 5.91 | CF20: 5.9 | CG20: 5.91 | CH20: 5.9 | CI20: 5.91 | CJ20: 2.95 | CK20: 0 | CL20: 0 | CM20: 0 | CN20: 0
C21: Summed Hourly Cashflow (already taxed) | E21: 0 | F21: =SweepValue1!$X$29*F17 -> 586.69162 | G21: =SweepValue1!$X$29*G17 -> 543.23298 | H21: =SweepValue1!$X$29*H17 -> 502.9935 | I21: =SweepValue1!$X$29*I17 -> 465.73472 | J21: =SweepValue1!$X$29*J17 -> 431.23585 | K21: =SweepValue1!$X$29*K17 -> 399.29246 | L21: =SweepValue1!$X$29*L17 -> 369.71524 | M21: =SweepValue1!$X$29*M17 -> 342.32892 | ... Y21: =SweepValue1!$X$29*Y17 -> 135.94353 | Z21: =SUM(E21:Y21) -> 6221.0428 | AA21: =SUM(Z21:Z24) -> 5661.2835 | BR21: MACRS Coefficient (15yr) | BT21: =BT20/100 -> 0 | BU21: =BU20/100 -> 0.05 | BV21: =BV20/100 -> 0.095 | BW21: =BW20/100 -> 0.0855 | BX21: =BX20/100 -> 0.077 | BY21: =BY20/100 -> 0.0693 | BZ21: =BZ20/100 -> 0.0623 | CA21: =CA20/100 -> 0.059 | ... CN21: =CN20/100 -> 0
C22: CAPEX Cashflow | E22: =E20*E16 -> -751.72893 | F22: =F20*F16 -> 0 | G22: =G20*G16 -> 0 | H22: =H20*H16 -> 0 | I22: =I20*I16 -> 0 | J22: =J20*J16 -> 0 | K22: =K20*K16 -> 0 | L22: =L20*L16 -> 0 | ... Y22: =Y20*Y16 -> 0 | Z22: =SUM(E22:Y22) -> -751.72893
C23: Depreciation + | E23: =-$E$20*E17/100*E18 -> 0 | F23: =-$E$20*F17*F19 -> 132.61983 | G23: =-$E$20*G17*G19 -> 210.44629 | H23: =-$E$20*H17*H19 -> 139.16132 | I23: =-$E$20*I17*I19 -> 92.016862 | J23: =-$E$20*J17*J19 -> 60.916183 | K23: =-$E$20*K17*K19 -> 56.340711 | L23: =-$E$20*L17*L19 -> 52.225808 | M23: =-$E$20*M17*M19 -> 24.151539 | ... X23: =-$E$20*X17*X19 -> 0 | Y23: =-$E$20*Y17/100*Y18 -> 0 | Z23: =SUM(E23:Y23) -> 767.87855
C24: Depreciation - | E24: =E18*E17/100*$E$22 -> 0 | F24: =-F23*F16 -> -99.464874 | G24: =-G23*G16 -> -157.83472 | H24: =-H23*H16 -> -104.37099 | I24: =-I23*I16 -> -69.012646 | J24: =-J23*J16 -> -45.687137 | K24: =-K23*K16 -> -42.255533 | L24: =-L23*L16 -> -39.169356 | M24: =-M23*M16 -> -18.113654 | ... X24: =-X23*X16 -> 0 | Y24: =Y18*Y17*$E$22 -> 0 | Z24: =SUM(E24:Y24) -> -575.90891
B25: SweepValue2 | C25: CAPEX | E25: =$D$109*($D$3/$D$110)^$D$111 -> -2003.2215 | F25: 0 | G25: 0 | H25: 0 | I25: 0 | J25: 0 | K25: 0 | L25: 0 | M25: 0 | N25: 0 | O25: 0 | P25: 0 | Q25: 0 | R25: 0 | S25: 0 | T25: 0 | U25: 0 | V25: 0 | W25: 0 | X25: 0 | Y25: 0
C26: Summed Hourly Cashflow (already taxed) | E26: 0 | F26: =SweepValue2!$X$29*F17 -> 1173.3961 | G26: =SweepValue2!$X$29*G17 -> 1086.4779 | H26: =SweepValue2!$X$29*H17 -> 1005.998 | I26: =SweepValue2!$X$29*I17 -> 931.47965 | J26: =SweepValue2!$X$29*J17 -> 862.48116 | K26: =SweepValue2!$X$29*K17 -> 798.59367 | L26: =SweepValue2!$X$29*L17 -> 739.43858 | M26: =SweepValue2!$X$29*M17 -> 684.66535 | ... Y26: =SweepValue2!$X$29*Y17 -> 271.89003 | Z26: =SUM(E26:Y26) -> 12442.222 | AA26: =SUM(Z26:Z29) -> 11323.479
C27: CAPEX Cashflow | E27: =E25*E16 -> -1502.4161 | F27: 0 | G27: 0 | H27: 0 | I27: 0 | J27: 0 | K27: 0 | L27: 0 | M27: 0 | N27: 0 | O27: 0 | P27: 0 | Q27: 0 | R27: 0 | S27: 0 | T27: 0 | U27: 0 | V27: 0 | W27: 0 | X27: 0 | Y27: 0 | Z27: =SUM(E27:Y27) -> -1502.4161
C28: Depreciation + | E28: =-$E$25*E17*E18/100 -> 0 | F28: =-$E$25*F17*F19 -> 265.05588 | G28: =-$E$25*G17*G19 -> 420.60094 | H28: =-$E$25*H17*H19 -> 278.12979 | I28: =-$E$25*I17*I19 -> 183.9062 | J28: =-$E$25*J17*J19 -> 121.74795 | K28: =-$E$25*K17*K19 -> 112.60334 | L28: =-$E$25*L17*L19 -> 104.37924 | M28: =-$E$25*M17*M19 -> 48.269609 | ... X28: =-$E$25*X17*X19 -> 0 | Y28: =-$E$25*Y17*Y18/100 -> 0 | Z28: =SUM(E28:Y28) -> 1534.693
C29: Depreciation - | E29: =$E$27*E17*E18/100 -> 0 | F29: =-F28*F16 -> -198.79191 | G29: =-G28*G16 -> -315.45071 | H29: =-H28*H16 -> -208.59734 | I29: =-I28*I16 -> -137.92965 | J29: =-J28*J16 -> -91.31096 | K29: =-K28*K16 -> -84.452508 | L29: =-L28*L16 -> -78.284431 | M29: =-M28*M16 -> -36.202207 | ... X29: =-X28*X16 -> 0 | Y29: =$E$27*Y17*Y18/100 -> 0 | Z29: =SUM(E29:Y29) -> -1151.0197
C33: Lifetime <= ProjectTime (Lifetime = 20) | AJ33: StartTime + Lifetime < ProjectTime Lifetime > ProjectTime (Lifetime = 25) | BR33: StartTime + Lifetime > ProjectTime |MACRS|+1 < |StartTime| (Lifetime = 40)
C36: PROJECT YEARS | E36: 0 | F36: 1 | G36: 2 | H36: 3 | I36: 4 | J36: 5 | K36: 6 | L36: 7 | M36: 8 | N36: 9 | O36: 10 | P36: 11 | Q36: 12 | R36: 13 | S36: 14 | T36: 15 | U36: 16 | V36: 17 | W36: 18 | X36: 19 | Y36: 20 | AJ36: PROJECT YEARS | AL36: 0 | AM36: 1 | AN36: 2 | AO36: 3 | AP36: 4 | AQ36: 5 | AR36: 6 | AS36: 7 | AT36: 8 | AU36: 9 | AV36: 10 | AW36: 11 | AX36: 12 | AY36: 13 | AZ36: 14 | BA36: 15 | BB36: 16 | BC36: 17 | BD36: 18 | BE36: 19 | BF36: 20 | BR36: PROJECT YEARS | BT36: 0 | BU36: 1 | BV36: 2 | BW36: 3 | BX36: 4 | BY36: 5 | BZ36: 6 | CA36: 7 | CB36: 8 | CC36: 9 | CD36: 10 | CE36: 11 | CF36: 12 | CG36: 13 | CH36: 14 | CI36: 15 | CJ36: 16 | CK36: 17 | CL36: 18 | CM36: 19 | CN36: 20
C37: COMPONENT YEARS | D37: Operations | E37: 5 | F37: 6 | G37: 7 | H37: 8 | I37: 9 | J37: 10 | K37: 11 | L37: 12 | M37: 13 | N37: 14 | O37: 15 | P37: 16 | Q37: 17 | R37: 18 | S37: 19 | T37: 20 | U37: 21 | V37: 22 | W37: 23 | X37: 24 | Y37: 25 | AJ37: COMPONENT YEARS | AK37: Operations | AL37: 10 | AM37: 11 | AN37: 12 | AO37: 13 | AP37: 14 | AQ37: 15 | AR37: 16 | AS37: 17 | AT37: 18 | AU37: 19 | AV37: 20 | AW37: 21 | AX37: 22 | AY37: 23 | AZ37: 24 | BA37: 25 | BB37: 26 | BC37: 27 | BD37: 28 | BE37: 29 | BF37: 30 | BR37: COMPONENT YEARS | BS37: Operations | BT37: 10 | BU37: 11 | BV37: 12 | BW37: 13 | BX37: 14 | BY37: 15 | BZ37: 16 | CA37: 17 | CB37: 18 | CC37: 19 | CD37: 20 | CE37: 21 | CF37: 22 | CG37: 23 | CH37: 24 | CI37: 25 | CJ37: 26 | CK37: 27 | CL37: 28 | CM37: 29 | CN37: 30
C38: COMPONENT YEARS | D38: Build | T38: SECOND | AJ38: COMPONENT YEARS | AK38: Build | BA38: SECOND | BR38: COMPONENT YEARS | BS38: Build
C39: MACRS YEARS | E39: 5 | F39: 6 | G39: 7 | H39: 8 | I39: 0 | J39: 0 | K39: 0 | L39: 0 | M39: 0 | N39: 0 | O39: 0 | P39: 0 | Q39: 0 | R39: 0 | S39: 0 | T39: 0 | U39: 1 | V39: 2 | W39: 3 | X39: 4 | Y39: 5 | AJ39: MACRS YEARS | AL39: 0 | AM39: 0 | AN39: 0 | AO39: 0 | AP39: 0 | AQ39: 0 | AR39: 0 | AS39: 0 | AT39: 0 | AU39: 0 | AV39: 0 | AW39: 0 | AX39: 0 | AY39: 0 | AZ39: 0 | BA39: 0 | BB39: 1 | BC39: 2 | BD39: 3 | BE39: 4 | BF39: 5 | BR39: MACRS YEARS | BT39: 0 | BU39: 0 | BV39: 0 | BW39: 0 | BX39: 0 | BY39: 0 | BZ39: 0 | CA39: 0 | CB39: 0 | CC39: 0 | CD39: 0 | CE39: 0 | CF39: 0 | CG39: 0 | CH39: 0 | CI39: 0 | CJ39: 0 | CK39: 0 | CL39: 0 | CM39: 0 | CN39: 0
C40: PROJECT YEARS | E40: -1 | F40: -2 | G40: -3 | H40: -4 | I40: -5 | AJ40: PROJECT YEARS | AL40: -1 | AM40: -2 | AN40: -3 | AO40: -4 | AP40: -5 | AQ40: -6 | AR40: -7 | AS40: -8 | AT40: -9 | AU40: -10 | BR40: PROJECT YEARS | BT40: -1 | BU40: -2 | BV40: -3 | BW40: -4 | BX40: -5 | BY40: -6 | BZ40: -7 | CA40: -8 | CB40: -9 | CC40: -10
C41: COMPONENT YEARS | D41: Operations | E41: 4 | F41: 3 | G41: 2 | H41: 1 | I41: - | AJ41: COMPONENT YEARS | AK41: Operations | AL41: 9 | AM41: 8 | AN41: 7 | AO41: 6 | AP41: 5 | AQ41: 4 | AR41: 3 | AS41: 2 | AT41: 1 | AU41: - | BR41: COMPONENT YEARS | BS41: Operations | BT41: 9 | BU41: 8 | BV41: 7 | BW41: 6 | BX41: 5 | BY41: 4 | BZ41: 3 | CA41: 2 | CB41: 1 | CC41: -
C42: COMPONENT YEARS | D42: Build | I42: FIRST | AJ42: COMPONENT YEARS | AK42: Build | AU42: FIRST | BR42: COMPONENT YEARS | BS42: Build | CC42: FIRST
C43: MACRS YEARS | E43: 4 | F43: 3 | G43: 2 | H43: 1 | I43: 0 | AJ43: MACRS YEARS | AL43: 0 | AM43: 8 | AN43: 7 | AO43: 6 | AP43: 5 | AQ43: 4 | AR43: 3 | AS43: 2 | AT43: 1 | AU43: 0 | BR43: MACRS YEARS | BT43: 0 | BU43: 8 | BV43: 7 | BW43: 6 | BX43: 5 | BY43: 4 | BZ43: 3 | CA43: 2 | CB43: 1 | CC43: 0
C45: PROJECT YEARS | E45: 0 | F45: 1 | G45: 2 | H45: 3 | I45: 4 | J45: 5 | K45: 6 | L45: 7 | M45: 8 | N45: 9 | O45: 10 | P45: 11 | Q45: 12 | R45: 13 | S45: 14 | T45: 15 | U45: 16 | V45: 17 | W45: 18 | X45: 19 | Y45: 20 | AJ45: PROJECT YEARS | AL45: 0 | AM45: 1 | AN45: 2 | AO45: 3 | AP45: 4 | AQ45: 5 | AR45: 6 | AS45: 7 | AT45: 8 | AU45: 9 | AV45: 10 | AW45: 11 | AX45: 12 | AY45: 13 | AZ45: 14 | BA45: 15 | BB45: 16 | BC45: 17 | BD45: 18 | BE45: 19 | BF45: 20 | BR45: PROJECT YEARS | BT45: 0 | BU45: 1 | BV45: 2 | BW45: 3 | BX45: 4 | BY45: 5 | BZ45: 6 | CA45: 7 | CB45: 8 | CC45: 9 | CD45: 10 | CE45: 11 | CF45: 12 | CG45: 13 | CH45: 14 | CI45: 15 | CJ45: 16 | CK45: 17 | CL45: 18 | CM45: 19 | CN45: 20
C46: MACRS YEARS | E46: 5 | F46: 6 | G46: 7 | H46: 8 | I46: 0 | J46: 0 | K46: 0 | L46: 0 | M46: 0 | N46: 0 | O46: 0 | P46: 0 | Q46: 0 | R46: 0 | S46: 0 | T46: 0 | U46: 1 | V46: 2 | W46: 3 | X46: 4 | Y46: 5 | AJ46: MACRS YEARS | AL46: 0 | AM46: 0 | AN46: 0 | AO46: 0 | AP46: 0 | AQ46: 0 | AR46: 0 | AS46: 0 | AT46: 0 | AU46: 0 | AV46: 0 | AW46: 0 | AX46: 0 | AY46: 0 | AZ46: 0 | BA46: 0 | BB46: 1 | BC46: 2 | BD46: 3 | BE46: 4 | BF46: 5 | BR46: MACRS YEARS | BT46: 0 | BU46: 0 | BV46: 0 | BW46: 0 | BX46: 0 | BY46: 0 | BZ46: 0 | CA46: 0 | CB46: 0 | CC46: 0 | CD46: 0 | CE46: 0 | CF46: 0 | CG46: 0 | CH46: 0 | CI46: 0 | CJ46: 0 | CK46: 0 | CL46: 0 | CM46: 0 | CN46: 0 | CQ46: MACRS 7yr
C47: MACRS Coefficient | E47: =J18/100 -> 0.0893 | F47: =K18/100 -> 0.0892 | G47: =L18/100 -> 0.0893 | H47: =M18/100 -> 0.0446 | I47: 0 | J47: 0 | K47: 0 | L47: 0 | M47: 0 | N47: 0 | O47: 0 | P47: 0 | Q47: 0 | R47: 0 | S47: 0 | T47: 0 | U47: =F18/100 -> 0.1429 | V47: =G18/100 -> 0.2449 | W47: =H18/100 -> 0.1749 | X47: =I18/100 -> 0.1249 | Y47: =J18/100 -> 0.0893 | AB47: StartTime=-5 | AJ47: MACRS Coefficient | AL47: 0 | AM47: 0 | AN47: 0 | AO47: 0 | AP47: 0 | AQ47: 0 | AR47: 0 | AS47: 0 | AT47: 0 | AU47: 0 | AV47: 0 | AW47: 0 | AX47: 0 | AY47: 0 | AZ47: 0 | BA47: 0 | BB47: =AM18/100 -> 0 | BC47: =AN18/100 -> 0 | BD47: =AO18/100 -> 0 | BE47: =AP18/100 -> 0 | BF47: =AQ18/100 -> 0 | BI47: StartTime=-10 | BR47: MACRS Coefficient | BT47: 0 | BU47: 0 | BV47: 0 | BW47: 0 | BX47: 0 | BY47: 0 | BZ47: 0 | CA47: 0 | CB47: 0 | CC47: 0 | CD47: 0 | CE47: 0 | CF47: 0 | CG47: 0 | CH47: 0 | CI47: 0 | CJ47: 0 | CK47: 0 | CL47: 0 | CM47: 0 | CN47: 0 | CQ47: StartTime=-10
B48: SweepValue1 | C48: CAPEX | E48: =E20 -> -1002.3052 | AB48: CORRECT | AI48: SweepValue1 | AJ48: CAPEX | AL48: =E48 -> -1002.3052 | BI48: CORRECT | BQ48: SweepValue1 | BR48: CAPEX | BT48: =AM48 -> 0 | CQ48: ERROR
C49: Summed Hourly Cashflow (already taxed) | E49: 0 | F49: =F21 -> 586.69162 | G49: =G21 -> 543.23298 | H49: =H21 -> 502.9935 | I49: =I21 -> 465.73472 | J49: =J21 -> 431.23585 | K49: =K21 -> 399.29246 | L49: =L21 -> 369.71524 | M49: =M21 -> 342.32892 | ... Y49: =Y21 -> 135.94353 | Z49: =SUM(E49:Y49) -> 6221.0428 | AA49: =SUM(Z49:Z52) -> 6105.2518 | AJ49: Summed Hourly Cashflow (already taxed) | AL49: 0 | AM49: =F49 -> 586.69162 | AN49: =G49 -> 543.23298 | AO49: =H49 -> 502.9935 | AP49: =I49 -> 465.73472 | AQ49: =J49 -> 431.23585 | AR49: =K49 -> 399.29246 | AS49: =L49 -> 369.71524 | AT49: =M49 -> 342.32892 | ... BF49: =Y49 -> 135.94353 | BG49: =SUM(AL49:BF49) -> 6221.0428 | BH49: =SUM(BG49:BG52) -> 6034.1237 | BR49: Summed Hourly Cashflow (already taxed) | BT49: 0 | BU49: =AN49 -> 543.23298 | BV49: =AO49 -> 502.9935 | BW49: =AP49 -> 465.73472 | BX49: =AQ49 -> 431.23585 | BY49: =AR49 -> 399.29246 | BZ49: =AS49 -> 369.71524 | CA49: =AT49 -> 342.32892 | CB49: =AU49 -> 316.97123 | ... CN49: =BG49 -> 6221.0428 | CO49: =SUM(BT49:CN49) -> 11855.394 | CP49: =SUM(CO49:CO52) -> 11855.394
C50: CAPEX Cashflow | E50: 0 | F50: =F48*F32 -> 0 | G50: =G48*G32 -> 0 | H50: =H48*H32 -> 0 | I50: =I48*I32 -> 0 | J50: =J48*J32 -> 0 | K50: =K48*K32 -> 0 | L50: =L48*L32 -> 0 | M50: =M48*M32 -> 0 | ... S50: =S48*S32 -> 0 | T50: =E48*T16*T17 -> -236.97631 | U50: =U48*U32 -> 0 | V50: =V48*V32 -> 0 | W50: =W48*W32 -> 0 | X50: =X48*X32 -> 0 | Y50: =Y48*Y32 -> 0 | Z50: =SUM(E50:Y50) -> -236.97631 | AJ50: CAPEX Cashflow | AL50: =AL48*AL32 -> 0 | AM50: =AM48*AM32 -> 0 | AN50: =AN48*AN32 -> 0 | AO50: =AO48*AO32 -> 0 | AP50: =AP48*AP32 -> 0 | AQ50: =AQ48*AQ32 -> 0 | AR50: =AR48*AR32 -> 0 | AS50: =AS48*AS32 -> 0 | ... AZ50: =AZ48*AZ32 -> 0 | BA50: =T50 -> -236.97631 | BB50: =BB48*BB32 -> 0 | BC50: =BC48*BC32 -> 0 | BD50: =BD48*BD32 -> 0 | BE50: =BE48*BE32 -> 0 | BF50: =BF48*BF32 -> 0 | BG50: =SUM(AL50:BF50) -> -236.97631 | BR50: CAPEX Cashflow | BT50: =BT48*BT32 -> 0 | BU50: =BU48*BU32 -> 0 | BV50: =BV48*BV32 -> 0 | BW50: =BW48*BW32 -> 0 | BX50: =BX48*BX32 -> 0 | BY50: =BY48*BY32 -> 0 | BZ50: =BZ48*BZ32 -> 0 | CA50: =CA48*CA32 -> 0 | ... CH50: =CH48*CH32 -> 0 | CI50: =BB50 -> 0 | CJ50: =CJ48*CJ32 -> 0 | CK50: =CK48*CK32 -> 0 | CL50: =CL48*CL32 -> 0 | CM50: =CM48*CM32 -> 0 | CN50: =CN48*CN32 -> 0 | CO50: =SUM(BT50:CN50) -> 0
C51: Depreciation + | E51: =-$E$48*E47*E17 -> 89.505858 | F51: =-$E$48*F47*F17 -> 82.782988 | G51: =-$E$48*G47*G17 -> 76.736847 | H51: =-$E$48*H47*H17 -> 35.486535 | I51: =-$E$48*I47*I17 -> 0 | J51: =-$E$48*J47*J17 -> 0 | K51: =-$E$48*K47*K17 -> 0 | L51: =-$E$48*L47*L17 -> 0 | ... Y51: =-$E$48*Y47*Y17 -> 19.203321 | Z51: =SUM(E51:Y51) -> 484.7413 | AJ51: Depreciation + | AL51: =-$E$20*AL33/100*AL45 -> 0 | AM51: =-$E$20*AM33/100*AM45 -> 0 | AN51: =-$E$20*AN33/100*AN45 -> 0 | AO51: =-$E$20*AO33/100*AO45 -> 0 | AP51: =-$E$20*AP33/100*AP45 -> 0 | AQ51: =-$E$20*AQ33/100*AQ45 -> 0 | AR51: =-$E$20*AR33/100*AR45 -> 0 | AS51: =-$E$20*AS33/100*AS45 -> 0 | ... BA51: =-$E$20*BA33/100*BA45 -> 0 | BB51: =U51 -> 41.807302 | BC51: =V51 -> 66.341447 | BD51: =W51 -> 43.869452 | BE51: =X51 -> 29.007552 | BF51: =Y51 -> 19.203321 | BG51: =SUM(AL51:BF51) -> 200.22908 | BR51: Depreciation + | BT51: =-$E$20*BT33/100*BT45 -> 0 | BU51: =-$E$20*BU33/100*BU45 -> 0 | BV51: =-$E$20*BV33/100*BV45 -> 0 | BW51: =-$E$20*BW33/100*BW45 -> 0 | BX51: =-$E$20*BX33/100*BX45 -> 0 | BY51: =-$E$20*BY33/100*BY45 -> 0 | BZ51: =-$E$20*BZ33/100*BZ45 -> 0 | CA51: =-$E$20*CA33/100*CA45 -> 0 | ... CN51: =-$E$20*CN33/100*CN45 -> 0 | CO51: =SUM(BT51:CN51) -> 0
C52: Depreciation - | E52: =-E51*E16 -> -67.129393 | F52: =-F51*F16 -> -62.087241 | G52: =-G51*G16 -> -57.552635 | H52: =-H51*H16 -> -26.614901 | I52: =-I51*I16 -> 0 | J52: =-J51*J16 -> 0 | K52: =-K51*K16 -> 0 | L52: =-L51*L16 -> 0 | ... Y52: =-Y51*Y16 -> -14.402491 | Z52: =SUM(E52:Y52) -> -363.55598 | AJ52: Depreciation - | AL52: =AL45*AL33/100*$E$22 -> 0 | AM52: =AM45*AM33/100*$E$22 -> 0 | AN52: =AN45*AN33/100*$E$22 -> 0 | AO52: =AO45*AO33/100*$E$22 -> 0 | AP52: =AP45*AP33/100*$E$22 -> 0 | AQ52: =AQ45*AQ33/100*$E$22 -> 0 | AR52: =AR45*AR33/100*$E$22 -> 0 | AS52: =AS45*AS33/100*$E$22 -> 0 | ... BA52: =BA45*BA33/100*$E$22 -> 0 | BB52: =U52 -> -31.355476 | BC52: =V52 -> -49.756085 | BD52: =W52 -> -32.902089 | BE52: =X52 -> -21.755664 | BF52: =Y52 -> -14.402491 | BG52: =SUM(AL52:BF52) -> -150.17181 | BR52: Depreciation - | BT52: =BT45*BT33/100*$E$22 -> 0 | BU52: =BU45*BU33/100*$E$22 -> 0 | BV52: =BV45*BV33/100*$E$22 -> 0 | BW52: =BW45*BW33/100*$E$22 -> 0 | BX52: =BX45*BX33/100*$E$22 -> 0 | BY52: =BY45*BY33/100*$E$22 -> 0 | BZ52: =BZ45*BZ33/100*$E$22 -> 0 | CA52: =CA45*CA33/100*$E$22 -> 0 | ... CN52: =CN45*CN33/100*$E$22 -> 0 | CO52: =SUM(BT52:CN52) -> 0
B53: SweepValue2 | C53: CAPEX | E53: =E25 -> -2003.2215 | AI53: SweepValue2 | AJ53: CAPEX | AL53: =E53 -> -2003.2215 | BQ53: SweepValue2 | BR53: CAPEX | BT53: =AM53 -> 0
C54: Summed Hourly Cashflow (already taxed) | E54: 0 | F54: =F26 -> 1173.3961 | G54: =G26 -> 1086.4779 | H54: =H26 -> 1005.998 | I54: =I26 -> 931.47965 | J54: =J26 -> 862.48116 | K54: =K26 -> 798.59367 | L54: =L26 -> 739.43858 | M54: =M26 -> 684.66535 | ... Y54: =Y26 -> 271.89003 | Z54: =SUM(E54:Y54) -> 12442.222 | AA54: =SUM(Z54:Z57) -> 12210.8 | AJ54: Summed Hourly Cashflow (already taxed) | AL54: 0 | AM54: =F54 -> 1173.3961 | AN54: =G54 -> 1086.4779 | AO54: =H54 -> 1005.998 | AP54: =I54 -> 931.47965 | AQ54: =J54 -> 862.48116 | AR54: =K54 -> 798.59367 | AS54: =L54 -> 739.43858 | AT54: =M54 -> 684.66535 | ... BF54: =Y54 -> 271.89003 | BG54: =SUM(AL54:BF54) -> 12442.222 | BH54: =SUM(BG54:BG57) -> 12068.643 | BR54: Summed Hourly Cashflow (already taxed) | BT54: 0 | BU54: =AN54 -> 1086.4779 | BV54: =AO54 -> 1005.998 | BW54: =AP54 -> 931.47965 | BX54: =AQ54 -> 862.48116 | BY54: =AR54 -> 798.59367 | BZ54: =AS54 -> 739.43858 | CA54: =AT54 -> 684.66535 | CB54: =AU54 -> 633.9494 | ... CN54: =BG54 -> 12442.222 | CO54: =SUM(BT54:CN54) -> 23711.048 | CP54: =SUM(CO54:CO57) -> 23711.048
C55: CAPEX Cashflow | E55: 0 | F55: 0 | G55: 0 | H55: 0 | I55: 0 | J55: 0 | K55: 0 | L55: 0 | M55: 0 | N55: 0 | O55: 0 | P55: 0 | Q55: 0 | R55: 0 | S55: 0 | T55: =E53*T16*T17 -> -473.62421 | U55: 0 | V55: 0 | W55: 0 | X55: 0 | Y55: 0 | Z55: =SUM(E55:Y55) -> -473.62421 | AJ55: CAPEX Cashflow | AL55: =AL53*AL32 -> 0 | AM55: 0 | AN55: 0 | AO55: 0 | AP55: 0 | AQ55: 0 | AR55: 0 | AS55: 0 | AT55: 0 | AU55: 0 | AV55: 0 | AW55: 0 | AX55: 0 | AY55: 0 | AZ55: 0 | BA55: =T55 -> -473.62421 | BB55: =U55 -> 0 | BC55: 0 | BD55: 0 | BE55: 0 | BF55: 0 | BG55: =SUM(AL55:BF55) -> -473.62421 | BR55: CAPEX Cashflow | BT55: =BT53*BT32 -> 0 | BU55: 0 | BV55: 0 | BW55: 0 | BX55: 0 | BY55: 0 | BZ55: 0 | CA55: 0 | CB55: 0 | CC55: 0 | CD55: 0 | CE55: 0 | CF55: 0 | CG55: 0 | CH55: 0 | CI55: =BB55 -> 0 | CJ55: =BC55 -> 0 | CK55: 0 | CL55: 0 | CM55: 0 | CN55: 0 | CO55: =SUM(BT55:CN55) -> 0
C56: Depreciation + | E56: =-$E$53*E47*E17 -> 178.88768 | F56: =-$E$53*F47*F17 -> 165.45125 | G56: =-$E$53*G47*G17 -> 153.36735 | H56: =-$E$53*H47*H17 -> 70.923892 | I56: =-$E$53*I47*I17 -> 0 | J56: =-$E$53*J47*J17 -> 0 | K56: =-$E$53*K47*K17 -> 0 | L56: =-$E$53*L47*L17 -> 0 | ... Y56: =-$E$53*Y47*Y17 -> 38.38003 | Z56: =SUM(E56:Y56) -> 968.81084 | AJ56: Depreciation + | AL56: =-$E$25*AL33*AL45/100 -> 0 | AM56: =-$E$25*AM33*AM45/100 -> 0 | AN56: =-$E$25*AN33*AN45/100 -> 0 | AO56: =-$E$25*AO33*AO45/100 -> 0 | AP56: =-$E$25*AP33*AP45/100 -> 0 | AQ56: =-$E$25*AQ33*AQ45/100 -> 0 | AR56: =-$E$25*AR33*AR45/100 -> 0 | AS56: =-$E$25*AS33*AS45/100 -> 0 | ... BA56: =-$E$25*BA33*BA45/100 -> 0 | BB56: =U56 -> 83.556667 | BC56: =V56 -> 132.59096 | BD56: =W56 -> 87.678109 | BE56: =X56 -> 57.974906 | BF56: =Y56 -> 38.38003 | BG56: =SUM(AL56:BF56) -> 400.18067 | BR56: Depreciation + | BT56: =-$E$25*BT33*BT45/100 -> 0 | BU56: =-$E$25*BU33*BU45/100 -> 0 | BV56: =-$E$25*BV33*BV45/100 -> 0 | BW56: =-$E$25*BW33*BW45/100 -> 0 | BX56: =-$E$25*BX33*BX45/100 -> 0 | BY56: =-$E$25*BY33*BY45/100 -> 0 | BZ56: =-$E$25*BZ33*BZ45/100 -> 0 | CA56: =-$E$25*CA33*CA45/100 -> 0 | ... CN56: =-$E$25*CN33*CN45/100 -> 0 | CO56: =SUM(BT56:CN56) -> 0
C57: Depreciation - | E57: =-E56*E16 -> -134.16576 | F57: =-F56*F16 -> -124.08844 | G57: =-G56*G16 -> -115.02551 | H57: =-H56*H16 -> -53.192919 | I57: =-I56*I16 -> 0 | J57: =-J56*J16 -> 0 | K57: =-K56*K16 -> 0 | L57: =-L56*L16 -> 0 | ... Y57: =-Y56*Y16 -> -28.785023 | Z57: =SUM(E57:Y57) -> -726.60813 | AJ57: Depreciation - | AL57: =$E$27*AL33*AL45/100 -> 0 | AM57: =$E$27*AM33*AM45/100 -> 0 | AN57: =$E$27*AN33*AN45/100 -> 0 | AO57: =$E$27*AO33*AO45/100 -> 0 | AP57: =$E$27*AP33*AP45/100 -> 0 | AQ57: =$E$27*AQ33*AQ45/100 -> 0 | AR57: =$E$27*AR33*AR45/100 -> 0 | AS57: =$E$27*AS33*AS45/100 -> 0 | ... BA57: =$E$27*BA33*BA45/100 -> 0 | BB57: =U57 -> -62.6675 | BC57: =V57 -> -99.443218 | BD57: =W57 -> -65.758582 | BE57: =X57 -> -43.481179 | BF57: =Y57 -> -28.785023 | BG57: =SUM(AL57:BF57) -> -300.1355 | BR57: Depreciation - | BT57: =$E$27*BT33*BT45/100 -> 0 | BU57: =$E$27*BU33*BU45/100 -> 0 | BV57: =$E$27*BV33*BV45/100 -> 0 | BW57: =$E$27*BW33*BW45/100 -> 0 | BX57: =$E$27*BX33*BX45/100 -> 0 | BY57: =$E$27*BY33*BY45/100 -> 0 | BZ57: =$E$27*BZ33*BZ45/100 -> 0 | CA57: =$E$27*CA33*CA45/100 -> 0 | ... CN57: =$E$27*CN33*CN45/100 -> 0 | CO57: =SUM(BT57:CN57) -> 0
BR62: StartTime + Lifetime > ProjectTime |MACRS|+1 >= |StartTime| (Lifetime = 40)
BQ65: Simulation | BR65: PROJECT YEARS | BT65: 0 | BU65: 1 | BV65: 2 | BW65: 3 | BX65: 4 | BY65: 5 | BZ65: 6 | CA65: 7 | CB65: 8 | CC65: 9 | CD65: 10 | CE65: 11 | CF65: 12 | CG65: 13 | CH65: 14 | CI65: 15 | CJ65: 16 | CK65: 17 | CL65: 18 | CM65: 19 | CN65: 20
BR66: COMPONENT YEARS | BS66: Operations | BT66: 10 | BU66: 11 | BV66: 12 | BW66: 13 | BX66: 14 | BY66: 15 | BZ66: 16 | CA66: 17 | CB66: 18 | CC66: 19 | CD66: 20 | CE66: 21 | CF66: 22 | CG66: 23 | CH66: 24 | CI66: 25 | CJ66: 26 | CK66: 27 | CL66: 28 | CM66: 29 | CN66: 30
BR67: COMPONENT YEARS | BS67: Build
BR68: MACRS YEARS | BT68: 10 | BU68: 11 | BV68: 12 | BW68: 13 | BX68: 14 | BY68: 15 | BZ68: 16 | CA68: 0 | CB68: 0 | CC68: 0 | CD68: 0 | CE68: 0 | CF68: 0 | CG68: 0 | CH68: 0 | CI68: 0 | CJ68: 0 | CK68: 0 | CL68: 0 | CM68: 0 | CN68: 0
BQ69: Prior to Simulation | BR69: PROJECT YEARS | BT69: -1 | BU69: -2 | BV69: -3 | BW69: -4 | BX69: -5 | BY69: -6 | BZ69: -7 | CA69: -8 | CB69: -9 | CC69: -10
BR70: COMPONENT YEARS | BS70: Operations | BT70: 9 | BU70: 8 | BV70: 7 | BW70: 6 | BX70: 5 | BY70: 4 | BZ70: 3 | CA70: 2 | CB70: 1 | CC70: -
BR71: COMPONENT YEARS | BS71: Build | CC71: FIRST
BR72: MACRS YEARS | BT72: 9 | BU72: 8 | BV72: 7 | BW72: 6 | BX72: 5 | BY72: 4 | BZ72: 3 | CA72: 2 | CB72: 1 | CC72: 0
BR74: PROJECT YEARS | BT74: 0 | BU74: 1 | BV74: 2 | BW74: 3 | BX74: 4 | BY74: 5 | BZ74: 6 | CA74: 7 | CB74: 8 | CC74: 9 | CD74: 10 | CE74: 11 | CF74: 12 | CG74: 13 | CH74: 14 | CI74: 15 | CJ74: 16 | CK74: 17 | CL74: 18 | CM74: 19 | CN74: 20
BR75: MACRS YEARS | BT75: 10 | BU75: 11 | BV75: 12 | BW75: 13 | BX75: 14 | BY75: 15 | BZ75: 16 | CA75: 0 | CB75: 0 | CC75: 0 | CD75: 0 | CE75: 0 | CF75: 0 | CG75: 0 | CH75: 0 | CI75: 0 | CJ75: 0 | CK75: 0 | CL75: 0 | CM75: 0 | CN75: 0 | CQ75: MACRS 15yr
BR76: MACRS Coefficient | BT76: =CD21 -> 0.059 | BU76: =CE21 -> 0.0591 | BV76: =CF21 -> 0.059 | BW76: =CG21 -> 0.0591 | BX76: =CH21 -> 0.059 | BY76: =CI21 -> 0.0591 | BZ76: =CJ21 -> 0.0295 | CA76: =CK21 -> 0 | CB76: 0 | CC76: 0 | CD76: 0 | CE76: 0 | CF76: 0 | CG76: 0 | CH76: 0 | CI76: 0 | CJ76: 0 | CK76: 0 | CL76: 0 | CM76: 0 | CN76: 0 | CQ76: StartTime=-10
BQ77: SweepValue1 | BR77: CAPEX | BT77: =E48 -> -1002.3052 | CQ77: ERROR
BR78: Summed Hourly Cashflow (already taxed) | BT78: 0 | BU78: =F49 -> 586.69162 | BV78: =G49 -> 543.23298 | BW78: =H49 -> 502.9935 | BX78: =I49 -> 465.73472 | BY78: =J49 -> 431.23585 | BZ78: =K49 -> 399.29246 | CA78: =L49 -> 369.71524 | CB78: =M49 -> 342.32892 | ... CN78: =Y49 -> 135.94353 | CO78: =SUM(BT78:CN78) -> 6221.0428 | CP78: =SUM(CO78:CO81) -> 6299.5734
BR79: CAPEX Cashflow | BT79: =BT77*BT61 -> 0 | BU79: =BU77*BU61 -> 0 | BV79: =BV77*BV61 -> 0 | BW79: =BW77*BW61 -> 0 | BX79: =BX77*BX61 -> 0 | BY79: =BY77*BY61 -> 0 | BZ79: =BZ77*BZ61 -> 0 | CA79: =CA77*CA61 -> 0 | ... CH79: =CH77*CH61 -> 0 | CI79: =BB79 -> 0 | CJ79: =CJ77*CJ61 -> 0 | CK79: =CK77*CK61 -> 0 | CL79: =CL77*CL61 -> 0 | CM79: =CM77*CM61 -> 0 | CN79: =CN77*CN61 -> 0 | CO79: =SUM(BT79:CN79) -> 0
BR80: Depreciation + | BT80: =-$BT$77*BT76*BT17 -> 59.136009 | BU80: =-$BT$77*BU76*BU17 -> 54.84837 | BV80: =-$BT$77*BV76*BV17 -> 50.699596 | BW80: =-$BT$77*BW76*BW17 -> 47.023637 | BX80: =-$BT$77*BX76*BX17 -> 43.466732 | BY80: =-$BT$77*BY76*BY17 -> 40.315189 | BZ80: =-$BT$77*BZ76*BZ17 -> 18.632858 | CA80: =-$BT$77*CA76*CA17 -> 0 | ... CF80: =-$BT$77*CF76*CF17 -> 0 | CG80: =-$E$20*CG62/100*CG74 -> 0 | CH80: =-$E$20*CH62/100*CH74 -> 0 | CI80: =-$E$20*CI62/100*CI74 -> 0 | CJ80: =BC80 -> 0 | CK80: =BD80 -> 0 | CL80: =BE80 -> 0 | CM80: =BF80 -> 0 | CN80: =BG80 -> 0 | CO80: =SUM(BT80:CN80) -> 314.12239
BR81: Depreciation - | BT81: =-BT80*BT16 -> -44.352007 | BU81: =-BU80*BU16 -> -41.136277 | BV81: =-BV80*BV16 -> -38.024697 | BW81: =-BW80*BW16 -> -35.267728 | BX81: =-BX80*BX16 -> -32.600049 | BY81: =-BY80*BY16 -> -30.236392 | BZ81: =-BZ80*BZ16 -> -13.974644 | CA81: =-CA80*CA16 -> 0 | CB81: =CB74*CB62/100*$E$22 -> 0 | CC81: =CC74*CC62/100*$E$22 -> 0 | CD81: =CD74*CD62/100*$E$22 -> 0 | CE81: =CE74*CE62/100*$E$22 -> 0 | CF81: =CF74*CF62/100*$E$22 -> 0 | CG81: =CG74*CG62/100*$E$22 -> 0 | CH81: =CH74*CH62/100*$E$22 -> 0 | CI81: =CI74*CI62/100*$E$22 -> 0 | CJ81: =BC81 -> 0 | CK81: =BD81 -> 0 | CL81: =BE81 -> 0 | CM81: =BF81 -> 0 | CN81: =BG81 -> 0 | CO81: =SUM(BT81:CN81) -> -235.59179
BQ82: SweepValue2 | BR82: CAPEX | BT82: =E53 -> -2003.2215
BR83: Summed Hourly Cashflow (already taxed) | BT83: 0 | BU83: =F54 -> 1173.3961 | BV83: =G54 -> 1086.4779 | BW83: =H54 -> 1005.998 | BX83: =I54 -> 931.47965 | BY83: =J54 -> 862.48116 | BZ83: =K54 -> 798.59367 | CA83: =L54 -> 739.43858 | CB83: =M54 -> 684.66535 | ... CN83: =Y54 -> 271.89003 | CO83: =SUM(BT83:CN83) -> 12442.222 | CP83: =SUM(CO83:CO86) -> 12599.174
BR84: CAPEX Cashflow | BT84: =BT82*BT61 -> 0 | BU84: 0 | BV84: 0 | BW84: 0 | BX84: 0 | BY84: 0 | BZ84: 0 | CA84: 0 | CB84: 0 | CC84: 0 | CD84: 0 | CE84: 0 | CF84: 0 | CG84: 0 | CH84: 0 | CI84: =BB84 -> 0 | CJ84: =BC84 -> 0 | CK84: 0 | CL84: 0 | CM84: 0 | CN84: 0 | CO84: =SUM(BT84:CN84) -> 0
BR85: Depreciation + | BT85: =-$BT$82*BT76*BT17 -> 118.19007 | BU85: =-$BT$82*BU76*BU17 -> 109.62073 | BV85: =-$BT$82*BV76*BV17 -> 101.32893 | BW85: =-$BT$82*BW76*BW17 -> 93.982108 | BX85: =-$BT$82*BX76*BX17 -> 86.873227 | BY85: =-$BT$82*BY76*BY17 -> 80.574509 | BZ85: =-$BT$82*BZ76*BZ17 -> 37.239895 | CA85: =-$BT$82*CA76*CA17 -> 0 | ... CC85: =-$BT$82*CC76*CC17 -> 0 | CD85: =-$E$25*CD62*CD74/100 -> 0 | CE85: =-$E$25*CE62*CE74/100 -> 0 | CF85: =-$E$25*CF62*CF74/100 -> 0 | CG85: =-$E$25*CG62*CG74/100 -> 0 | CH85: =-$E$25*CH62*CH74/100 -> 0 | CI85: =-$E$25*CI62*CI74/100 -> 0 | CJ85: =BC85 -> 0 | CK85: =BD85 -> 0 | CL85: =BE85 -> 0 | CM85: =BF85 -> 0 | CN85: =BG85 -> 0 | CO85: =SUM(BT85:CN85) -> 627.80947
BR86: Depreciation - | BT86: =-BT85*BT16 -> -88.64255 | BU86: =-BU85*BU16 -> -82.215548 | BV86: =-BV85*BV16 -> -75.996699 | BW86: =-BW85*BW16 -> -70.486581 | BX86: =-BX85*BX16 -> -65.15492 | BY86: =-BY85*BY16 -> -60.430882 | BZ86: =-BZ85*BZ16 -> -27.929921 | CA86: =-CA85*CA16 -> 0 | CB86: =-CB85*CB16 -> 0 | CC86: =$E$27*CC62*CC74/100 -> 0 | CD86: =$E$27*CD62*CD74/100 -> 0 | CE86: =$E$27*CE62*CE74/100 -> 0 | CF86: =$E$27*CF62*CF74/100 -> 0 | CG86: =$E$27*CG62*CG74/100 -> 0 | CH86: =$E$27*CH62*CH74/100 -> 0 | CI86: =$E$27*CI62*CI74/100 -> 0 | CJ86: =BC86 -> 0 | CK86: =BD86 -> 0 | CL86: =BE86 -> 0 | CM86: =BF86 -> 0 | CN86: =BG86 -> 0 | CO86: =SUM(BT86:CN86) -> -470.8571
BY98: With Depreciation
BY99: LifeTime | CA99: L<T | CB99: L>T
BY100: StartTime | CA100: L-S<T | CB100: L-S < T | CC100: L-S > T
BY101: MACRS | CA101: M | CB101: M | CC101: M+1 < |-S| | CD101: M+1 ≥ |-S|
BY102: Current Result: | CA102: OK | CB102: OK | CC102: ERROR | CD102: ERROR
BY103: Expected Result: | CA103: OK | CB103: OK | CC103: No Capex, No Amort | CD103: No Capex, YES Amort
C107: These numbers are hardcoded from the given heron input file. Changing these values will affect final answer. | BY107: LifeTime | CA107: L<T | CB107: L>T
C108: CAPEX | BY108: StartTime | CA108: L-S<T | CB108: L-S < T | CC108: L-S > T
C109: reference_price (a) | D109: -10000 | BY109: Current Result: | CA109: OK | CB109: OK | CC109: ERROR
C110: reference_driver (D') | D110: 10 | BY110: Expected Result: | CA110: OK | CB110: OK | CC110: No Capex
C111: scaling_factor (X) | D111: 0.999
C112: driver (D) | D112: =D2 -> 1
C113: type | D113: one-time
C114: period | D114: -
C115: taxable | D115: TRUE
C116: inflation | D116: none
C117: mult_target | D117: FALSE
C118: depreciate | D118: 5
C120: FOM
C121: reference_price (a) | D121: -100
C122: reference_driver (D') | D122: 10
C123: scaling_factor (X) | D123: 0.999
C124: driver (D) | D124: =D112 -> 1
C125: type | D125: repeating
C126: period | D126: year
C127: taxable | D127: FALSE
C128: inflation | D128: none
C129: mult_target | D129: FALSE
C131: VOM
C132: reference_price (a) | D132: -1
...
